Workbook
Name BP: Base[[#Headers],[Data_Padronizada]]
Name BP: Base[[#Headers],[Data_Padronizada]]
Name Painel: Base[[#Headers],[Data_Padronizada]]
Name SegmentaçãodeDados_Classificação_técnica: #N/A
Name SegmentaçãodeDados_Coordenador: #N/A
Name SegmentaçãodeDados_Dia_Semana: #N/A
Name SegmentaçãodeDados_Estado: #N/A
Name SegmentaçãodeDados_Gestor_Macro: #N/A
Name SegmentaçãodeDados_Resumo_TIPO: #N/A
Name SegmentaçãodeDados_Status_da_Atividade: #N/A
Name SegmentaçãodeDados_Supervisor: #N/A

Sheet FORÇA DE TRABALHO
A3: TOTAL HC | B3: =SUM(B4:B5) -> 16
A4: ATIVO | B4: {=SUMPRODUCT(SUBTOTAL(103,OFFSET(I15,ROW(I15:I1000)-ROW(I15),0,1)),--ISNUMBER(MATCH(I15:I1000,{"ATIVO"},0)))} -> 14
A5: ABSETEÍSMO | B5: {=SUMPRODUCT(SUBTOTAL(103,OFFSET(I15,ROW(I15:I1000)-ROW(I15),0,1)),--ISNUMBER(MATCH(I15:I1000,{"AUSENTE";"FÉRIAS";"BH";"ATESTADO";"LICENÇA";"TREINAMENTO";"FERIADO";"DESLIGADO";"FOLGA"},0)))} -> 2
A6: FERIADO | B6: {=SUMPRODUCT(SUBTOTAL(103,OFFSET(I15,ROW(I15:I1000)-ROW(I15),0,1)),--ISNUMBER(MATCH(I15:I1000,{"FERIADO"},0)))} -> 0
A7: FÉRIAS | B7: {=SUMPRODUCT(SUBTOTAL(103,OFFSET($I$15,ROW($I$15:$I$1001)-ROW($I$15),0,1)),--ISNUMBER(MATCH($I$15:$I$1001,{"FÉRIAS"},0)))} -> 2
A8: ATESTADO | B8: {=SUMPRODUCT(SUBTOTAL(103,OFFSET($I$15,ROW($I$15:$I$1001)-ROW($I$15),0,1)),--ISNUMBER(MATCH($I$15:$I$1001,{"ATESTADO"},0)))} -> 0
A9: FOLGA | B9: {=SUMPRODUCT(SUBTOTAL(103,OFFSET($I$15,ROW($I$15:$I$1001)-ROW($I$15),0,1)),--ISNUMBER(MATCH($I$15:$I$1001,{"FOLGA"},0)))} -> 0 | E9: =TEXT(E10, "dddd") -> quinta-feira | F9: =TEXT(F10, "dddd") -> sexta-feira | G9: =TEXT(G10, "dddd") -> sábado | H9: =TEXT(H10, "dddd") -> domingo | I9: =TEXT(I10, "dddd") -> segunda-feira | J9: =TEXT(J10, "dddd") -> terça-feira | K9: =TEXT(K10, "dddd") -> quarta-feira
A10: BH | B10: {=SUMPRODUCT(SUBTOTAL(103,OFFSET($I$15,ROW($I$15:$I$1001)-ROW($I$15),0,1)),--ISNUMBER(MATCH($I$15:$I$1001,{"BH"},0)))} -> 0 | E10: =Tabela1[[#Headers],[01/10/2026]] -> 01/10/2026 | F10: =Tabela1[[#Headers],[02/10/2026]] -> 02/10/2026 | G10: =Tabela1[[#Headers],[03/10/2026]] -> 03/10/2026 | H10: =Tabela1[[#Headers],[04/10/2026]] -> 04/10/2026 | I10: =Tabela1[[#Headers],[05/10/2026]] -> 05/10/2026 | J10: =Tabela1[[#Headers],[06/10/2026]] -> 06/10/2026 | K10: 46302 | L10: 46303
A11: LICENÇA | B11: {=SUMPRODUCT(SUBTOTAL(103,OFFSET($I$15,ROW($I$15:$I$1001)-ROW($I$15),0,1)),--ISNUMBER(MATCH($I$15:$I$1001,{"LICENÇA"},0)))} -> 0 | C11: HC TOTAL | E11: {=SUMPRODUCT(SUBTOTAL(103,OFFSET(E19,ROW(E15:E64)-ROW(E19),0,1)),--(E15:E64<>""))} -> 16 | F11: {=SUMPRODUCT(SUBTOTAL(103,OFFSET(F19,ROW(F15:F64)-ROW(F19),0,1)),--(F15:F64<>""))} -> 16 | G11: {=SUMPRODUCT(SUBTOTAL(103,OFFSET(G19,ROW(G15:G64)-ROW(G19),0,1)),--(G15:G64<>""))} -> 16 | H11: {=SUMPRODUCT(SUBTOTAL(103,OFFSET(H19,ROW(H15:H64)-ROW(H19),0,1)),--(H15:H64<>""))} -> 16 | I11: {=SUMPRODUCT(SUBTOTAL(103,OFFSET(I19,ROW(I15:I64)-ROW(I19),0,1)),--(I15:I64<>""))} -> 16 | J11: {=SUMPRODUCT(SUBTOTAL(103,OFFSET(J19,ROW(J15:J64)-ROW(J19),0,1)),--(J15:J64<>""))} -> 16 | K11: {=SUMPRODUCT(SUBTOTAL(103,OFFSET(K19,ROW(K15:K64)-ROW(K19),0,1)),--(K15:K64<>""))} -> 16 | L11: {=SUMPRODUCT(SUBTOTAL(103,OFFSET(L19,ROW(L15:L64)-ROW(L19),0,1)),--(L15:L64<>""))} -> 16
A12: TREINAMENTO | B12: {=SUMPRODUCT(SUBTOTAL(103,OFFSET($I$15,ROW($I$15:$I$1001)-ROW($I$15),0,1)),--ISNUMBER(MATCH($I$15:$I$1001,{"TREINAMENTO"},0)))} -> 0 | C12: HC DIA | E12: {=SUMPRODUCT(SUBTOTAL(103,OFFSET(E14,ROW(E14:E1006)-ROW(E14),0,1)),--ISNUMBER(MATCH(E14:E1006,{"ATIVO"},0)))} -> 16 | F12: {=SUMPRODUCT(SUBTOTAL(103,OFFSET(F14,ROW(F14:F1006)-ROW(F14),0,1)),--ISNUMBER(MATCH(F14:F1006,{"ATIVO"},0)))} -> 15 | G12: {=SUMPRODUCT(SUBTOTAL(103,OFFSET(G14,ROW(G14:G1006)-ROW(G14),0,1)),--ISNUMBER(MATCH(G14:G1006,{"ATIVO"},0)))} -> 0 | H12: {=SUMPRODUCT(SUBTOTAL(103,OFFSET(H14,ROW(H14:H1006)-ROW(H14),0,1)),--ISNUMBER(MATCH(H14:H1006,{"ATIVO"},0)))} -> 0 | I12: {=SUMPRODUCT(SUBTOTAL(103,OFFSET(I14,ROW(I14:I1006)-ROW(I14),0,1)),--ISNUMBER(MATCH(I14:I1006,{"ATIVO"},0)))} -> 14 | J12: {=SUMPRODUCT(SUBTOTAL(103,OFFSET(J14,ROW(J14:J1006)-ROW(J14),0,1)),--ISNUMBER(MATCH(J14:J1006,{"ATIVO"},0)))} -> 14 | K12: {=SUMPRODUCT(SUBTOTAL(103,OFFSET(K14,ROW(K14:K1006)-ROW(K14),0,1)),--ISNUMBER(MATCH(K14:K1006,{"ATIVO"},0)))} -> 14 | L12: {=SUMPRODUCT(SUBTOTAL(103,OFFSET(L14,ROW(L14:L1006)-ROW(L14),0,1)),--ISNUMBER(MATCH(L14:L1006,{"ATIVO"},0)))} -> 14
A13: DESLIGADO | B13: {=SUMPRODUCT(SUBTOTAL(103,OFFSET($I$15,ROW($I$15:$I$1001)-ROW($I$15),0,1)),--ISNUMBER(MATCH($I$15:$I$1001,{"DESLIGADO"},0)))} -> 0 | C13: Absenteismo do dia | E13: =IFERROR((E11-E12)/E11,0) -> 0 | F13: =IFERROR((F11-F12)/F11,0) -> 0.0625 | G13: =IFERROR((G11-G12)/G11,0) -> 1 | H13: =IFERROR((H11-H12)/H11,0) -> 1 | I13: =IFERROR((I11-I12)/I11,0) -> 0.125 | J13: =IFERROR((J11-J12)/J11,0) -> 0.125 | K13: =IFERROR((K11-K12)/K11,0) -> 0.125 | L13: =IFERROR((L11-L12)/L11,0) -> 0.125
A14: RESUMO CARGO | B14: Gestor Macro | C14: Nome | D14: UF | E14: 01/10/2026 | F14: 02/10/2026 | G14: 03/10/2026 | H14: 04/10/2026 | I14: 05/10/2026 | J14: 06/10/2026 | K14: 07/10/20262 | L14: 08/10/20263
A15: TÉCNICO TX | B15: RICARDO ALVES DOS SANTOS | C15: WILTON BRAGA DA SILVA | D15: AL | E15: ATIVO | F15: ATIVO | G15: FOLGA | H15: SOBRE AVISO | I15: ATIVO | J15: ATIVO | K15: ATIVO | L15: ATIVO
A16: TÉCNICO TX | B16: RICARDO ALVES DOS SANTOS | C16: HUMBERTO DOUGLAS ARAUJO SANTOS | D16: AL | E16: ATIVO | F16: ATIVO | G16: SOBRE AVISO | H16: SOBRE AVISO | I16: ATIVO | J16: ATIVO | K16: ATIVO | L16: ATIVO
A17: TÉCNICO REDE | B17: WEDSON FERNANDES DA SILVA | C17: ANDERSON COSTA DOS SANTOS | D17: BA | E17: ATIVO | F17: ATIVO | G17: FOLGA | H17: FOLGA | I17: ATIVO | J17: ATIVO | K17: ATIVO | L17: ATIVO
A18: TÉCNICO REDE | B18: WEDSON FERNANDES DA SILVA | C18: JOAO ALBERTO MENDES GUEDES | D18: BA | E18: ATIVO | F18: ATIVO | G18: FOLGA | H18: FOLGA | I18: FÉRIAS | J18: FÉRIAS | K18: FÉRIAS | L18: ATIVO
A19: TÉCNICO REDE | B19: WEDSON FERNANDES DA SILVA | C19: LUCAS DOS SANTOS COELHO | D19: BA | E19: ATIVO | F19: ATIVO | G19: FOLGA | H19: FOLGA | I19: ATIVO | J19: ATIVO | K19: ATIVO | L19: ATIVO
A20: TÉCNICO REDE | B20: WEDSON FERNANDES DA SILVA | C20: MOISES SANTOS BUISINE | D20: BA | E20: ATIVO | F20: ATIVO | G20: FOLGA | H20: FOLGA | I20: ATIVO | J20: ATIVO | K20: ATIVO | L20: ATIVO
A21: TÉCNICO REDE | B21: WEDSON FERNANDES DA SILVA | C21: TALITA WEDJA FELIPE DA SILVA | D21: BA | E21: ATIVO | F21: ATIVO | G21: FOLGA | H21: FOLGA | I21: ATIVO | J21: ATIVO | K21: ATIVO | L21: ATIVO
A22: TÉCNICO REDE | B22: WEDSON FERNANDES DA SILVA | C22: THIAGO PEREIRA LIMA | D22: BA | E22: ATIVO | F22: ATIVO | G22: FOLGA | H22: FOLGA | I22: ATIVO | J22: ATIVO | K22: ATIVO | L22: ATIVO
A23: TÉCNICO REDE | B23: WEDSON FERNANDES DA SILVA | C23: VALDEILTON DE SOUZA DO NASCIMENTO | D23: BA | E23: ATIVO | F23: ATIVO | G23: FOLGA | H23: FOLGA | I23: ATIVO | J23: ATIVO | K23: ATIVO | L23: ATIVO
A24: TÉCNICO TX | B24: WEDSON FERNANDES DA SILVA | C24: JHONATAN MONTEIRO DE ANDRADE | D24: BA | E24: ATIVO | F24: ATIVO | G24: FOLGA | H24: FOLGA | I24: ATIVO | J24: ATIVO | K24: ATIVO | L24: ATIVO
A25: TÉCNICO TX | B25: WEDSON FERNANDES DA SILVA | C25: MARCIO DE SOUSA LIMA | D25: BA | E25: ATIVO | F25: ATIVO | G25: FOLGA | H25: FOLGA | I25: FÉRIAS | J25: FÉRIAS | K25: FÉRIAS | L25: FÉRIAS
... A63: TÉCNICO TX | B63: WEDSON FERNANDES DA SILVA | C63: GEORGE MENEZES DOS SANTOS | D63: SE | E63: ATIVO | F63: ATIVO | G63: FOLGA | H63: FOLGA | I63: ATIVO | J63: ATIVO | K63: ATIVO | L63: ATIVO

Sheet Média produtiva
C4: Média Mês | D4: 46266 | E4: 46267 | F4: 46268 | G4: 46269 | H4: 46270 | I4: 46273 | J4: 46274 | K4: 46275 | L4: 46276 | M4: 46277 | N4: 46279 | O4: 46280 | P4: 46281 | Q4: 46282 | R4: 46283 | S4: 46284 | T4: 46286 | U4: 46287 | V4: 46288 | W4: 46289 | X4: 46290 | Y4: 46291 | Z4: 46292 | AA4: 46293 | AB4: 46294 | AC4: 46295
C5: ='Produção TOA'!I1 -> 1634 | D5: ='Produção TOA'!M9 -> 2.2432432 | E5: ='Produção TOA'!N9 -> 2.0285714 | F5: ='Produção TOA'!O9 -> 1.95 | G5: ='Produção TOA'!P9 -> 1.9 | H5: ='Produção TOA'!Q9 -> 2.3333333 | I5: ='Produção TOA'!R9 -> 2.1025641 | J5: ='Produção TOA'!S9 -> 2.2564103 | K5: ='Produção TOA'!T9 -> 1.9459459 | ... V5: ='Produção TOA'!AE9 -> 2.2682927

Sheet Din
I2: Contagem de Recurso | J2: Rótulos de Coluna
A3: Técnicos | B3: Média_Produtiva | E3: Técnicos | F3: Dias Trabalhado | I3: Técnicos | J3: 46266 | K3: 46267 | L3: 46268 | M3: 46269 | N3: 46270 | O3: 46273 | P3: 46274 | Q3: 46275 | R3: 46276 | S3: 46277 | T3: 46279 | U3: 46280 | V3: 46281 | W3: 46282 | X3: 46283 | Y3: 46284 | Z3: 46286 | AA3: 46287 | AB3: 46288 | AC3: 46289 | AD3: 46290 | AE3: 46291 | AF3: 46292 | AG3: 46293 | AH3: 46294 | AI3: 46295
A4: LUCIANO MIGUEL DA SILVA | B4: 4 | E4: TALITA WEDJA FELIPE DA SILVA | F4: 23 | I4: ADÉCIO JÂNIO PEREIRA DE SOUSA | J4: 1 | K4: 1 | L4: 2 | M4: 2 | O4: 2 | P4: 4 | Q4: 2 | R4: 4 | T4: 2 | U4: 4 | V4: 4 | W4: 3 | X4: 1 | Z4: 2 | AA4: 1 | AB4: 4 | AC4: 1 | AD4: 1 | AG4: 3 | AH4: 3 | AI4: 1
A5: FRANCY ANA ALEXANDRINO CLAUDIO | B5: 3.3684211 | E5: EDMILSON HONORATO DE SANTANA JUNIOR | F5: 23 | I5: ALANA FERREIRA DE LIMA | L5: 1 | M5: 1 | O5: 1 | P5: 1 | Q5: 1 | R5: 1 | T5: 2 | U5: 1 | AA5: 2 | AB5: 3 | AC5: 2 | AD5: 2 | AG5: 3 | AI5: 2
A6: JAIRON VIEIRA ALVES | B6: 3 | E6: MOISES SANTOS BUISINE | F6: 22 | I6: ALDIR GOES DOS SANTOS | O6: 2 | Q6: 2 | T6: 1 | U6: 2 | W6: 2 | Z6: 2 | AA6: 2 | AB6: 2 | AC6: 1 | AG6: 1 | AH6: 2 | AI6: 2
A7: FERNANDO PINHEIRO DA SILVA JUNIOR | B7: 2.8095238 | E7: JOAO ALBERTO MENDES GUEDES | F7: 22 | I7: ALEXANDRE BORGES DA SILVA | J7: 1 | K7: 1 | L7: 2 | N7: 1 | O7: 1 | T7: 2 | W7: 2 | X7: 1 | Y7: 1 | AA7: 2 | AB7: 2 | AC7: 3 | AD7: 3 | AG7: 4 | AH7: 2 | AI7: 3
A8: EDSON TAVARES DA SILVA JUNIOR | B8: 2.6363636 | E8: ELIAS PEREIRA PASSOS FILHO | F8: 22 | I8: ANDERSON COSTA DOS SANTOS | J8: 1 | L8: 2 | M8: 2 | O8: 2 | P8: 3 | Q8: 1 | R8: 2 | S8: 1 | T8: 3 | U8: 1 | V8: 2 | W8: 1 | X8: 1 | Z8: 1 | AC8: 2 | AD8: 1 | AG8: 1 | AH8: 1 | AI8: 3
A9: HELIO SANDRO MONTEIRO PEIXOTO | B9: 2.5714286 | E9: CARLOS EDUARDO DA SILVA QUEIROZ | F9: 22 | I9: ANTONIO GALDINO DA SILVA NETO | K9: 1 | L9: 1 | M9: 1 | O9: 1 | P9: 1 | Q9: 1 | U9: 2 | V9: 1 | X9: 1 | Z9: 1 | AA9: 1 | AB9: 1 | AC9: 1 | AD9: 1 | AG9: 1 | AH9: 1
A10: PAULO ROBERTO DA SILVA | B10: 2.4210526 | E10: LUCAS DOS SANTOS COELHO | F10: 22 | I10: CARLOS ANDRE SANTOS LIMA | J10: 1 | K10: 1 | M10: 2 | T10: 2 | U10: 1 | V10: 1 | W10: 1 | Z10: 2 | AA10: 1 | AB10: 1 | AC10: 1 | AD10: 3
A11: CARLOS EDUARDO DA SILVA | B11: 2.2941176 | E11: ALEXANDRE BORGES DA SILVA | F11: 22 | I11: CARLOS EDUARDO DA SILVA | O11: 2 | P11: 2 | Q11: 2 | R11: 3 | T11: 3 | U11: 4 | V11: 3 | W11: 1 | X11: 2 | Z11: 1 | AA11: 2 | AB11: 3 | AC11: 2 | AD11: 2 | AG11: 3 | AH11: 2 | AI11: 2
A12: ADÉCIO JÂNIO PEREIRA DE SOUSA | B12: 2.2857143 | E12: ANDERSON COSTA DOS SANTOS | F12: 22 | I12: CARLOS EDUARDO DA SILVA QUEIROZ | J12: 3 | K12: 3 | L12: 1 | M12: 2 | O12: 2 | P12: 4 | Q12: 3 | R12: 2 | T12: 2 | U12: 2 | V12: 3 | W12: 2 | Y12: 1 | Z12: 1 | AA12: 1 | AB12: 1 | AC12: 2 | AD12: 2 | AG12: 3 | AH12: 5 | AI12: 3
A13: EDMILSON HONORATO DE SANTANA JUNIOR | B13: 2.2173913 | E13: EDSON TAVARES DA SILVA JUNIOR | F13: 22 | I13: DANILO COSTA CASSEMIRO DA SILVA | Z13: 1 | AA13: 2 | AB13: 3 | AC13: 2 | AD13: 2 | AG13: 1 | AH13: 1 | AI13: 1
A14: CARLOS EDUARDO DA SILVA QUEIROZ | B14: 2.1818182 | E14: VALDEILTON DE SOUZA DO NASCIMENTO | F14: 22 | I14: EBER BORGES DE SOUZA | J14: 2 | K14: 1 | L14: 2 | M14: 3 | N14: 1 | O14: 3 | P14: 2 | Q14: 1
A15: FRANCISCO EDVALDO CARDOSO CARNEIRO | B15: 2.15 | E15: ADÉCIO JÂNIO PEREIRA DE SOUSA | F15: 21 | I15: EDMILSON HONORATO DE SANTANA JUNIOR | J15: 2 | K15: 3 | L15: 2 | M15: 2 | P15: 2 | Q15: 3 | R15: 2 | T15: 1 | U15: 1 | V15: 2 | W15: 1 | X15: 2 | Y15: 3 | Z15: 2 | AA15: 2 | AB15: 4 | AC15: 3 | AD15: 3 | AG15: 3 | AH15: 5 | AI15: 3
A16: RAFAELA ALVES FACUNDO | B16: 2.1428571 | E16: RAFAELA ALVES FACUNDO | F16: 21 | I16: EDSON TAVARES DA SILVA JUNIOR | J16: 3 | K16: 4 | L16: 4 | M16: 4 | O16: 5 | P16: 2 | Q16: 2 | R16: 2 | T16: 2 | U16: 2 | V16: 3 | W16: 1 | X16: 2 | Z16: 4 | AA16: 2 | AB16: 6 | AC16: 1 | AD16: 2 | AF16: 2 | AG16: 1 | AH16: 2 | AI16: 2
A17: SILVIA JOELIA DE SOUSA GUIMARAES | B17: 2.0555556 | E17: THIAGO PEREIRA LIMA | F17: 21 | I17: ELIAS PEREIRA PASSOS FILHO | J17: 2 | K17: 3 | L17: 3 | M17: 2 | O17: 2 | P17: 2 | Q17: 2 | T17: 1 | U17: 2 | V17: 2 | X17: 1 | Y17: 1 | Z17: 1 | AB17: 3 | AC17: 1 | AD17: 3 | AG17: 1 | AH17: 2 | AI17: 3
A18: JOSE WELLINTON SOUZA SILVA | B18: 1.9473684 | E18: GILSON PATROCINIO DOS SANTOS ALENCAR | F18: 21 | I18: FERNANDO PINHEIRO DA SILVA JUNIOR | J18: 3 | K18: 4 | L18: 3 | M18: 4 | O18: 5 | P18: 2 | Q18: 2 | R18: 1 | T18: 2 | U18: 2 | V18: 2 | X18: 2 | Z18: 4 | AA18: 1 | AB18: 4 | AC18: 2 | AD18: 4 | AG18: 2 | AH18: 4 | AI18: 6
A19: HUMBERTO DOUGLAS ARAUJO SANTOS | B19: 1.9230769 | E19: SANDRA GABRIELA DOS ANJOS BARBOSA | F19: 21 | I19: FRANCISCO EDVALDO CARDOSO CARNEIRO | J19: 2 | K19: 2 | L19: 1 | M19: 2 | P19: 2 | Q19: 1 | R19: 2 | T19: 3 | U19: 5 | V19: 2 | W19: 2 | X19: 1 | Z19: 1 | AA19: 2 | AB19: 2 | AC19: 4 | AD19: 3 | AG19: 2 | AH19: 2 | AI19: 2
A20: JANECLEYTON RICARDO JUCA | B20: 1.8571429 | E20: LUCIANO MIGUEL DA SILVA | F20: 21 | I20: FRANCY ANA ALEXANDRINO CLAUDIO | J20: 3 | K20: 3 | L20: 4 | O20: 2 | P20: 3 | Q20: 3 | R20: 5 | T20: 3 | U20: 3 | V20: 3 | W20: 3 | X20: 3 | Z20: 4 | AA20: 5 | AB20: 4 | AC20: 3 | AD20: 4 | AH20: 3 | AI20: 3
A21: WILTON BRAGA DA SILVA | B21: 1.8421053 | E21: FERNANDO PINHEIRO DA SILVA JUNIOR | F21: 21 | I21: GEORGE MENEZES DOS SANTOS | M21: 2 | O21: 2 | P21: 2 | Q21: 2 | R21: 2 | T21: 1 | U21: 3 | V21: 2 | W21: 1 | X21: 1 | Z21: 1 | AA21: 2 | AB21: 2 | AC21: 1 | AD21: 3 | AG21: 1 | AI21: 4
A22: WENDERSON DA COSTA BARBOSA | B22: 1.8095238 | E22: MARCIO DE SOUSA LIMA | F22: 21 | I22: GILSON PATROCINIO DOS SANTOS ALENCAR | J22: 2 | M22: 1 | O22: 2 | P22: 2 | Q22: 1 | R22: 2 | T22: 1 | U22: 2 | V22: 1 | W22: 1 | X22: 1 | Y22: 1 | AA22: 2 | AB22: 1 | AC22: 2 | AD22: 1 | AG22: 3 | AH22: 3 | AI22: 2
A23: MARCIO DE SOUSA LIMA | B23: 1.8095238 | E23: WENDERSON DA COSTA BARBOSA | F23: 21 | I23: HELIO SANDRO MONTEIRO PEIXOTO | J23: 1 | K23: 4 | L23: 3 | M23: 1 | O23: 3 | P23: 2 | Q23: 1 | R23: 4 | T23: 4 | U23: 3 | V23: 3 | W23: 4 | X23: 3 | Z23: 3 | AA23: 2 | AB23: 3 | AC23: 1 | AD23: 4 | AG23: 2 | AH23: 1 | AI23: 2
A24: JEAN GALVÃO OLIVEIRA | B24: 1.7894737 | E24: HELIO SANDRO MONTEIRO PEIXOTO | F24: 21 | I24: HUMBERTO DOUGLAS ARAUJO SANTOS | J24: 3 | K24: 1 | L24: 1 | M24: 2 | Y24: 2 | Z24: 4 | AA24: 3 | AB24: 2 | AC24: 2 | AG24: 2 | AH24: 1 | AI24: 2
A25: JOSE WILSON GOMES DA SILVA | B25: 1.75 | E25: LAISE BRITO BOTELHO | F25: 20 | I25: JAIRON VIEIRA ALVES | J25: 3 | K25: 2 | L25: 4 | M25: 1 | N25: 5 | O25: 2 | P25: 3 | Q25: 5 | R25: 2
A26: JOSE ALVES DE SOUZA JUNIOR | B26: 1.7222222 | E26: GEORGE MENEZES DOS SANTOS | F26: 20 | I26: JANECLEYTON RICARDO JUCA | J26: 2 | K26: 1 | L26: 2 | M26: 2 | N26: 1 | O26: 3 | P26: 2
A27: VALDEILTON DE SOUZA DO NASCIMENTO | B27: 1.6818182 | E27: FRANCISCO EDVALDO CARDOSO CARNEIRO | F27: 20 | I27: JEAN GALVÃO OLIVEIRA | J27: 3 | K27: 3 | L27: 1 | M27: 2 | O27: 1 | Q27: 2 | R27: 2 | T27: 2 | U27: 2 | V27: 2 | W27: 2 | AA27: 1 | AB27: 1 | AC27: 1 | AD27: 2 | AG27: 3 | AH27: 2 | AI27: 2
A28: ELIAS PEREIRA PASSOS FILHO | B28: 1.6818182 | E28: SEVERINO INOCENCIO PEDROZA FILHO | F28: 20 | I28: JHONATAN MONTEIRO DE ANDRADE | J28: 1 | L28: 1 | M28: 2 | O28: 1 | P28: 4 | Q28: 1 | R28: 2 | T28: 2 | U28: 2 | V28: 2 | W28: 1 | X28: 1 | Z28: 1 | AG28: 1 | AH28: 1 | AI28: 2
A29: EBER BORGES DE SOUZA | B29: 1.6666667 | E29: ALANA FERREIRA DE LIMA | F29: 20 | I29: JOAO ALBERTO MENDES GUEDES | J29: 1 | K29: 1 | L29: 2 | M29: 1 | N29: 3 | O29: 2 | Q29: 2 | R29: 1 | T29: 2 | U29: 2 | V29: 3 | W29: 1 | X29: 2 | AB29: 1 | AC29: 1 | AD29: 1 | AG29: 2 | AH29: 2 | AI29: 1
A30: MOISES SANTOS BUISINE | B30: 1.6363636 | E30: JHONATAN MONTEIRO DE ANDRADE | F30: 20 | I30: JOAO FRANCISCO DE BRITO UCHOA | J30: 3 | K30: 3 | L30: 1 | AA30: 1 | AB30: 1 | AC30: 2 | AD30: 1 | AG30: 1 | AI30: 1
A31: TALITA WEDJA FELIPE DA SILVA | B31: 1.6086957 | E31: LUCIANO RODRIGUES FARIAS DA SILVA | F31: 19 | I31: JONATA GOMES DE SOUZA | P31: 1 | Q31: 1 | R31: 1 | T31: 2 | U31: 2 | V31: 1 | W31: 1 | X31: 1 | Z31: 1 | AA31: 4 | AB31: 2 | AC31: 3 | AD31: 1 | AG31: 1 | AH31: 1 | AI31: 1
A32: GEORGE MENEZES DOS SANTOS | B32: 1.6 | E32: JEAN GALVÃO OLIVEIRA | F32: 19 | I32: JOSE ALVES DE SOUZA JUNIOR | K32: 2 | L32: 1 | M32: 1 | P32: 2 | Q32: 3 | R32: 2 | U32: 2 | V32: 3 | W32: 2 | Z32: 1 | AA32: 2 | AB32: 1 | AC32: 4 | AG32: 1 | AH32: 1 | AI32: 3
A33: JONATA GOMES DE SOUZA | B33: 1.5 | E33: PEDRO ARTHUR ALMEIDA CARTAXO | F33: 19 | I33: JOSE AVELINO DE QUEIROZ NETO | L33: 1 | M33: 1 | O33: 3 | P33: 1 | R33: 1 | V33: 1 | W33: 1 | Z33: 1 | AA33: 1 | AB33: 2 | AC33: 2 | AG33: 1 | AH33: 1 | AI33: 1
A34: GILSON PATROCINIO DOS SANTOS ALENCAR | B34: 1.4761905 | E34: JOSE WELLINTON SOUZA SILVA | F34: 19 | I34: JOSE WELLINTON SOUZA SILVA | J34: 4 | K34: 1 | L34: 3 | M34: 1 | O34: 2 | P34: 3 | Q34: 2 | R34: 2 | T34: 2 | U34: 1 | V34: 2 | W34: 1 | X34: 2 | Z34: 3 | AA34: 2 | AB34: 1 | AG34: 1 | AH34: 2 | AI34: 2
A35: LUCIANO RODRIGUES FARIAS DA SILVA | B35: 1.4210526 | E35: WILTON BRAGA DA SILVA | F35: 19 | I35: JOSE WILSON GOMES DA SILVA | J35: 2 | K35: 2 | L35: 3 | O35: 2 | P35: 3 | T35: 1 | V35: 1 | W35: 2 | X35: 1 | Z35: 2 | AA35: 2 | AB35: 1 | AC35: 1 | AD35: 2 | AH35: 2 | AI35: 1
A36: JOAO ALBERTO MENDES GUEDES | B36: 1.4090909 | E36: FRANCY ANA ALEXANDRINO CLAUDIO | F36: 19 | I36: LAISE BRITO BOTELHO | J36: 1 | L36: 2 | M36: 2 | O36: 1 | P36: 2 | T36: 1 | U36: 1 | V36: 1 | W36: 1 | X36: 2 | AC36: 1 | AG36: 1 | AH36: 1 | AI36: 1
A37: ALEXANDRE BORGES DA SILVA | B37: 1.4090909 | E37: PAULO ROBERTO DA SILVA | F37: 19 | I37: LUCAS DOS SANTOS COELHO | J37: 1 | L37: 2 | M37: 1 | O37: 2 | P37: 3 | Q37: 1 | R37: 2 | S37: 1 | T37: 3 | U37: 1 | V37: 2 | W37: 1 | X37: 1 | Z37: 1 | AC37: 2 | AD37: 1 | AG37: 1 | AH37: 1 | AI37: 3
A38: ANDERSON COSTA DOS SANTOS | B38: 1.4090909 | E38: SILVIA JOELIA DE SOUSA GUIMARAES | F38: 18 | I38: LUCIANO MIGUEL DA SILVA | J38: 7 | K38: 7 | L38: 4 | M38: 2 | O38: 4 | P38: 2 | Q38: 3 | R38: 1 | T38: 3 | U38: 5 | V38: 5 | W38: 1 | X38: 4 | Z38: 4 | AA38: 3 | AB38: 3 | AC38: 4 | AD38: 2 | AG38: 6 | AH38: 13 | AI38: 1
A39: JOAO FRANCISCO DE BRITO UCHOA | B39: 1.4 | E39: ANTONIO GALDINO DA SILVA NETO | F39: 18 | I39: LUCIANO RODRIGUES FARIAS DA SILVA | J39: 2 | M39: 1 | O39: 1 | Q39: 1 | R39: 2 | T39: 1 | U39: 1 | V39: 2 | W39: 2 | Z39: 1 | AA39: 2 | AB39: 2 | AC39: 1 | AD39: 3 | AG39: 2 | AH39: 2 | AI39: 1
A40: LUCAS DOS SANTOS COELHO | B40: 1.3636364 | E40: JOSE ALVES DE SOUZA JUNIOR | F40: 18 | I40: MARCIO DE SOUSA LIMA | J40: 3 | L40: 3 | M40: 5 | O40: 3 | P40: 4 | R40: 2 | T40: 1 | U40: 2 | V40: 2 | W40: 4 | X40: 1 | Z40: 1 | AB40: 1 | AC40: 1 | AD40: 2 | AH40: 1 | AI40: 2
A41: SEVERINO INOCENCIO PEDROZA FILHO | B41: 1.35 | E41: CARLOS ANDRE SANTOS LIMA | F41: 18 | I41: MOISES SANTOS BUISINE | J41: 1 | K41: 2 | L41: 2 | M41: 2 | N41: 3 | O41: 2 | P41: 3 | Q41: 2 | R41: 3 | T41: 2 | U41: 2 | V41: 2 | W41: 1 | X41: 1 | AB41: 2 | AC41: 1 | AD41: 1 | AG41: 2 | AH41: 1 | AI41: 1
A42: PEDRO ARTHUR ALMEIDA CARTAXO | B42: 1.3157895 | E42: CARLOS EDUARDO DA SILVA | F42: 17 | I42: PAULO ROBERTO DA SILVA | J42: 1 | K42: 1 | L42: 1 | M42: 2 | O42: 1 | P42: 3 | Q42: 3 | R42: 3 | U42: 4 | V42: 2 | W42: 2 | X42: 2 | Z42: 2 | AA42: 3 | AB42: 3 | AC42: 4 | AD42: 4 | AH42: 3 | AI42: 2
A43: JHONATAN MONTEIRO DE ANDRADE | B43: 1.25 | E43: JOSE AVELINO DE QUEIROZ NETO | F43: 17 | I43: PEDRO ARTHUR ALMEIDA CARTAXO | J43: 1 | K43: 1 | M43: 1 | P43: 1 | Q43: 1 | R43: 1 | T43: 3 | U43: 1 | V43: 1 | W43: 1 | X43: 1 | Z43: 1 | AA43: 2 | AB43: 2 | AC43: 2 | AD43: 1 | AG43: 2 | AH43: 1 | AI43: 1
A44: SANDRA GABRIELA DOS ANJOS BARBOSA | B44: 1.2380952 | E44: ALDIR GOES DOS SANTOS | F44: 17 | I44: RAFAELA ALVES FACUNDO | J44: 3 | K44: 1 | L44: 1 | M44: 3 | O44: 3 | P44: 3 | Q44: 2 | R44: 4 | T44: 2 | U44: 3 | V44: 3 | W44: 1 | X44: 2 | Z44: 1 | AA44: 2 | AB44: 4 | AC44: 1 | AG44: 1 | AH44: 2 | AI44: 3
A45: ALDIR GOES DOS SANTOS | B45: 1.2352941 | E45: JOSE WILSON GOMES DA SILVA | F45: 16 | I45: RICARDO SILVA DE DEUS | K45: 1 | L45: 2 | M45: 1 | AC45: 1 | AD45: 1 | AG45: 1 | AH45: 1 | AI45: 1
A46: DANILO COSTA CASSEMIRO DA SILVA | B46: 1.1818182 | E46: JONATA GOMES DE SOUZA | F46: 16 | I46: SANDRA GABRIELA DOS ANJOS BARBOSA | J46: 1 | K46: 2 | L46: 1 | P46: 1 | R46: 1 | T46: 1 | U46: 1 | V46: 2 | W46: 2 | Y46: 1 | Z46: 2 | AB46: 1 | AC46: 2 | AD46: 3 | AG46: 1 | AH46: 2 | AI46: 2
A47: ALANA FERREIRA DE LIMA | B47: 1.15 | E47: HUMBERTO DOUGLAS ARAUJO SANTOS | F47: 13 | I47: SEVERINO INOCENCIO PEDROZA FILHO | J47: 2 | L47: 2 | M47: 1 | O47: 1 | Q47: 1 | R47: 2 | T47: 1 | U47: 1 | V47: 1 | W47: 2 | Z47: 1 | AA47: 2 | AB47: 2 | AC47: 1 | AD47: 3 | AG47: 2 | AH47: 1 | AI47: 1
A48: JOSE AVELINO DE QUEIROZ NETO | B48: 1.0588235 | E48: DANILO COSTA CASSEMIRO DA SILVA | F48: 11 | I48: SILVIA JOELIA DE SOUSA GUIMARAES | J48: 4 | K48: 2 | L48: 3 | M48: 4 | O48: 3 | P48: 3 | Q48: 2 | R48: 3 | S48: 1 | T48: 2 | U48: 2 | V48: 2 | X48: 2 | Z48: 1 | AB48: 2 | AC48: 1
A49: RICARDO SILVA DE DEUS | B49: 1 | E49: JOAO FRANCISCO DE BRITO UCHOA | F49: 10 | I49: TALITA WEDJA FELIPE DA SILVA | J49: 1 | K49: 2 | M49: 1 | O49: 1 | P49: 1 | Q49: 4 | R49: 5 | S49: 1 | T49: 3 | U49: 1 | V49: 1 | W49: 2 | X49: 1 | AA49: 1 | AB49: 3 | AC49: 1 | AE49: 1 | AG49: 3 | AH49: 2 | AI49: 2
A50: ANTONIO GALDINO DA SILVA NETO | B50: 0.94444444 | E50: EBER BORGES DE SOUZA | F50: 9 | I50: THIAGO PEREIRA LIMA | K50: 1 | L50: 1 | M50: 1 | O50: 1 | P50: 1 | R50: 1 | U50: 1 | V50: 2 | AC50: 1 | AD50: 2 | AG50: 1 | AI50: 1
A51: CARLOS ANDRE SANTOS LIMA | B51: 0.94444444 | E51: JAIRON VIEIRA ALVES | F51: 9 | I51: VALDEILTON DE SOUZA DO NASCIMENTO | J51: 1 | K51: 2 | L51: 1 | M51: 2 | O51: 2 | P51: 2 | Q51: 2 | R51: 2 | S51: 1 | T51: 2 | U51: 2 | V51: 2 | W51: 2 | X51: 1 | Z51: 2 | AA51: 1 | AB51: 3 | AC51: 2 | AD51: 2 | AG51: 1 | AH51: 1 | AI51: 1
A52: LAISE BRITO BOTELHO | B52: 0.9 | E52: RICARDO SILVA DE DEUS | F52: 9 | I52: WENDERSON DA COSTA BARBOSA | J52: 3 | K52: 1 | L52: 1 | M52: 3 | O52: 2 | P52: 2 | Q52: 2 | R52: 4 | T52: 2 | U52: 3 | V52: 2 | X52: 1 | Z52: 1 | AA52: 1 | AB52: 2 | AC52: 1 | AG52: 1 | AH52: 3 | AI52: 3
A53: THIAGO PEREIRA LIMA | B53: 0.66666667 | E53: JANECLEYTON RICARDO JUCA | F53: 7 | I53: WILTON BRAGA DA SILVA | J53: 2 | K53: 1 | L53: 1 | O53: 2 | P53: 2 | Q53: 2 | R53: 2 | T53: 1 | U53: 3 | W53: 1 | X53: 2 | Z53: 3 | AA53: 2 | AB53: 2 | AC53: 1 | AD53: 2 | AG53: 2 | AH53: 2 | AI53: 2

Sheet Mensal
B2: REPARO
B3: Jun | F3: Jul | J3: Ago
B4: Total | C4: Med. Men. | D4: H.C | E4: M. Tec. | F4: Total | G4: Med. Men. | H4: H.C | I4: M. Tec. | J4: Total | K4: Med. Men. | L4: H.C | M4: M. Tec.
A5: DIEGO SOARES LOPES | B5: 146 | C5: =AVERAGE(B5/21) -> 6.952381 | D5: 12 | E5: =AVERAGE(B5/D5) -> 12.166667 | F5: 142 | G5: =AVERAGE(F5/21) -> 6.7619048 | H5: 7 | I5: =AVERAGE(F5/H5) -> 20.285714 | J5: 142 | K5: =AVERAGE(J5/21) -> 6.7619048 | L5: 7 | M5: =AVERAGE(J5/L5) -> 20.285714
A6: RICARDO ALVES DOS SANTOS | B6: 279 | C6: =AVERAGE(B6/21) -> 13.285714 | D6: 18 | E6: =AVERAGE(B6/D6) -> 15.5 | F6: 354 | G6: =AVERAGE(F6/21) -> 16.857143 | H6: 18 | I6: =AVERAGE(F6/H6) -> 19.666667 | J6: 354 | K6: =AVERAGE(J6/21) -> 16.857143 | L6: 18 | M6: =AVERAGE(J6/L6) -> 19.666667
A7: WEDSON FERNANDES DA SILVA | B7: 113 | C7: =AVERAGE(B7/21) -> 5.3809524 | D7: 22 | E7: =AVERAGE(B7/D7) -> 5.1363636 | F7: 100 | G7: =AVERAGE(F7/21) -> 4.7619048 | H7: 16 | I7: =AVERAGE(F7/H7) -> 6.25 | J7: 100 | K7: =AVERAGE(J7/21) -> 4.7619048 | L7: 16 | M7: =AVERAGE(J7/L7) -> 6.25
B12: ATIVAÇÃO
B13: Jun | F13: Jul | J13: Ago
B14: Total | C14: Med. Men. | D14: H.C | E14: M. Tec. | F14: Total | G14: Med. Men. | H14: H.C | I14: M. Tec. | J14: Total | K14: Med. Men. | L14: H.C | M14: M. Tec.
A15: DIEGO SOARES LOPES | B15: 93 | C15: =AVERAGE(B15/21) -> 4.4285714 | D15: 10 | E15: =AVERAGE(B15/D15) -> 9.3 | F15: 83 | G15: =AVERAGE(F15/21) -> 3.952381 | H15: 11 | I15: =AVERAGE(F15/H15) -> 7.5454545 | J15: 129 | K15: =AVERAGE(J15/21) -> 6.1428571 | L15: 14 | M15: =AVERAGE(J15/L15) -> 9.2142857
A16: RICARDO ALVES DOS SANTOS | B16: 133 | C16: =AVERAGE(B16/21) -> 6.3333333 | D16: 17 | E16: =AVERAGE(B16/D16) -> 7.8235294 | F16: 130 | G16: =AVERAGE(F16/21) -> 6.1904762 | H16: 19 | I16: =AVERAGE(F16/H16) -> 6.8421053 | J16: 160 | K16: =AVERAGE(J16/21) -> 7.6190476 | L16: 14 | M16: =AVERAGE(J16/L16) -> 11.428571
A17: WEDSON FERNANDES DA SILVA | B17: 95 | C17: =AVERAGE(B17/21) -> 4.5238095 | D17: 22 | E17: =AVERAGE(B17/D17) -> 4.3181818 | F17: 118 | G17: =AVERAGE(F17/21) -> 5.6190476 | H17: 21 | I17: =AVERAGE(F17/H17) -> 5.6190476 | J17: 117 | K17: =AVERAGE(J17/21) -> 5.5714286 | L17: 17 | M17: =AVERAGE(J17/L17) -> 6.8823529
B20: CONSTRUÇÃO
B21: Jun | F21: Jul | J21: Ago
B22: Total | C22: Med. Men. | D22: H.C | E22: M. Tec. | F22: Total | G22: Med. Men. | H22: H.C | I22: M. Tec. | J22: Total | K22: Med. Men. | L22: H.C | M22: M. Tec.
A23: DIEGO SOARES LOPES | B23: 58 | C23: =AVERAGE(B23/21) -> 2.7619048 | D23: 6 | E23: =AVERAGE(B23/D23) -> 9.6666667 | F23: 35 | G23: =AVERAGE(F23/21) -> 1.6666667 | H23: 5 | I23: =AVERAGE(F23/H23) -> 7 | J23: 68 | K23: =AVERAGE(J23/21) -> 3.2380952 | L23: 7 | M23: =AVERAGE(J23/L23) -> 9.7142857
A24: RICARDO ALVES DOS SANTOS | B24: 48 | C24: =AVERAGE(B24/21) -> 2.2857143 | D24: 8 | E24: =AVERAGE(B24/D24) -> 6 | F24: 59 | G24: =AVERAGE(F24/21) -> 2.8095238 | H24: 9 | I24: =AVERAGE(F24/H24) -> 6.5555556 | J24: 60 | K24: =AVERAGE(J24/21) -> 2.8571429 | L24: 6 | M24: =AVERAGE(J24/L24) -> 10
A25: WEDSON FERNANDES DA SILVA | B25: 10 | C25: =AVERAGE(B25/21) -> 0.47619048 | D25: 8 | E25: =AVERAGE(B25/D25) -> 1.25 | F25: 38 | G25: =AVERAGE(F25/21) -> 1.8095238 | H25: 7 | I25: =AVERAGE(F25/H25) -> 5.4285714 | J25: 15 | K25: =AVERAGE(J25/21) -> 0.71428571 | L25: 5 | M25: =AVERAGE(J25/L25) -> 3

Sheet Produção TOA
H1: =SUM(ResumoProducao[Produção]) -> 1634 | I1: =H1/_xlfn.AGGREGATE(4,6,ResumoProducao[Dias Trabalhado]) -> 1634 | J1: =_xlfn.AGGREGATE(4,6,ResumoProducao[Média Produtiva do Mês:]) -> 84 | K1: =_xlfn.AGGREGATE(5,6,ResumoProducao[Média Produtiva do Mês:]) -> 9
M6: 46266 | N6: 46267 | O6: 46268 | P6: 46269 | Q6: 46270 | R6: 46273 | S6: 46274 | T6: 46275 | U6: 46276 | V6: 46277 | W6: 46279 | X6: 46280 | Y6: 46281 | Z6: 46282 | AA6: 46283 | AB6: 46284 | AC6: 46286 | AD6: 46287 | AE6: 46288 | AF6: 46289 | AG6: 46290 | AH6: 46291 | AI6: 46292 | AJ6: 46293 | AK6: 46294 | AL6: 46295
L7: HC TOTAL | M7: {=SUMPRODUCT(SUBTOTAL(103,OFFSET($L$13,ROW($L$13:$L$58)-ROW($L$13),0,1)),--($L$13:$L$58<>""))} -> 46 | N7: =M7 -> 46 | O7: =N7 -> 46 | P7: =O7 -> 46 | Q7: =P7 -> 46 | R7: =Q7 -> 46 | S7: =R7 -> 46 | T7: =S7 -> 46 | U7: =T7 -> 46 | ... AP7: =AO7 -> 46
L8: Absenteismo do dia | M8: =IF(M11>0,(M7-M11)/M7,"") -> 0.19565217 | N8: =IF(N11>0,(N7-N11)/N7,"") -> 0.23913043 | O8: =IF(O11>0,(O7-O11)/O7,"") -> 0.13043478 | P8: =IF(P11>0,(P7-P11)/P7,"") -> 0.13043478 | Q8: =IF(Q11>0,(Q7-Q11)/Q7,"") -> 0.86956522 | R8: =IF(R11>0,(R7-R11)/R7,"") -> 0.15217391 | S8: =IF(S11>0,(S7-S11)/S7,"") -> 0.15217391 | T8: =IF(T11>0,(T7-T11)/T7,"") -> 0.19565217 | ... AP8: =IF(AP11>0,(AP7-AP11)/AP7,"")
L9: Produtividade geral dia | M9: =IFERROR(M10/M11,0) -> 2.2432432 | N9: =IFERROR(N10/N11,0) -> 2.0285714 | O9: =IFERROR(O10/O11,0) -> 1.95 | P9: =IF(P11>0,P10/P11,"") -> 1.9 | Q9: =IF(Q11>0,Q10/Q11,"") -> 2.3333333 | R9: =IF(R11>0,R10/R11,"") -> 2.1025641 | S9: =IF(S11>0,S10/S11,"") -> 2.2564103 | T9: =IF(T11>0,T10/T11,"") -> 1.9459459 | U9: =IF(U11>0,U10/U11,"") -> 2.2432432 | V9: =IF(V11>0,V10/V11,"") -> 1 | W9: =IF(W11>0,W10/W11,"") -> 1.9473684 | ... AP9: =IF(AP11>0,AP10/AP11,"")
L10: Producao geral dia | M10: =SUM(M13:M95) -> 83 | N10: =SUM(N13:N95) -> 71 | O10: =SUM(O13:O95) -> 78 | P10: =SUM(P13:P95) -> 76 | Q10: =SUM(Q13:Q95) -> 14 | R10: =SUM(R13:R95) -> 82 | S10: =SUM(S13:S95) -> 88 | T10: =SUM(T13:T95) -> 72 | ... AL10: =SUM(AL13:AL95) -> 88 | AM10: =SUM(AM14:AM95) -> 0 | AN10: =SUM(AN14:AN95) -> 0 | AO10: =SUM(AO14:AO95) -> 0 | AP10: =SUM(AP14:AP95) -> 0
L11: HC Dia | M11: =COUNT(M13:M58) -> 37 | N11: =COUNT(N13:N81) -> 35 | O11: =COUNT(O13:O81) -> 40 | P11: =COUNT(P13:P81) -> 40 | Q11: =COUNT(Q13:Q81) -> 6 | R11: =COUNT(R13:R81) -> 39 | S11: =COUNT(S13:S81) -> 39 | T11: =COUNT(T13:T81) -> 37 | U11: =COUNT(U13:U81) -> 37 | ... AM11: =COUNT(AM13:AM81) -> 0 | AN11: =COUNT(AN14:AN81) -> 0 | AO11: =COUNT(AO14:AO81) -> 0 | AP11: =COUNT(AP14:AP81) -> 0
H12: Produção | I12: Média Produtiva do Mês: | J12: Dias Trabalhado | K12: Quartil | L12: Técnicos | M12: {=IF(_xlfn.XLOOKUP(L12,Din!$I$3:$I$100,Din!$J$3:$AN$100,"")="", "", _xlfn.XLOOKUP(L12,Din!$I$3:$I$100,Din!$J$3:$AN$100,""))} -> 46266 | N12: 46267 | O12: 46268 | P12: 46269 | Q12: 46270 | R12: 46273 | S12: 46274 | T12: 46275 | U12: 46276 | V12: 46277 | W12: 46279 | X12: 46280 | Y12: 46281 | Z12: 46282 | AA12: 46283 | AB12: 46284 | AC12: 46286 | AD12: 46287 | AE12: 46288 | AF12: 46289 | AG12: 46290 | AH12: 46291 | AI12: 46292 | AJ12: 46293 | AK12: 46294 | AL12: 46295
H13: =SUM(M13:AQ13) -> 84 | I13: =ResumoProducao[[#This Row],[Produção]]/ResumoProducao[[#This Row],[Dias Trabalhado]] -> 84 | J13: {=SUMPRODUCT(('FORÇA DE TRABALHO'!$C$15:$C$1007=L13)*('FORÇA DE TRABALHO'!$E$15:$E$1007="ATIVO"))} -> 1 | K13: =IF(I13<2,"4Q",IF(I13<=3,"3Q",IF(I13<=3.9,"2Q","1Q"))) -> 1Q | L13: =IF(Din!A4="","",Din!A4) -> LUCIANO MIGUEL DA SILVA | M13: {=IFERROR( _xlfn.LET( _xlpm.Prod,INDEX(Din!$J$4:$AR$1000, MATCH($L13,Din!$I$4:$I$1000,0), MATCH(M$6,Din!$J$3:$AO$3,0)), _xlpm.Status,INDEX('FORÇA DE TRABALHO'!$E$15:$E$999, MATCH($L13,'FORÇA DE TRABALHO'!$C$15:$C$999,0), MATCH(M$6+0,'FORÇA DE TRABALHO'!$E$14:$E$14+0,0)), IF( OR(_xlpm.Prod="",_xlpm.Prod=0), IF(_xlpm.Status="ATIVO",0,_xlpm.Status), _xlpm.Prod ) ), "")} -> 7 | N13: {=IFERROR( _xlfn.LET( _xlpm.Prod,INDEX(Din!$J$4:$AR$1000, MATCH($L13,Din!$I$4:$I$1000,0), MATCH(N$6,Din!$J$3:$AO$3,0)), _xlpm.Status,INDEX('FORÇA DE TRABALHO'!$E$15:$E$999, MATCH($L13,'FORÇA DE TRABALHO'!$C$15:$C$999,0), MATCH(N$6+0,'FORÇA DE TRABALHO'!$E$14:$E$14+0,0)), IF( OR(_xlpm.Prod="",_xlpm.Prod=0), IF(_xlpm.Status="ATIVO",0,_xlpm.Status), _xlpm.Prod ) ), "")} -> 7 | O13: {=IFERROR( _xlfn.LET( _xlpm.Prod,INDEX(Din!$J$4:$AR$1000, MATCH($L13,Din!$I$4:$I$1000,0), MATCH(O$6,Din!$J$3:$AO$3,0)), _xlpm.Status,INDEX('FORÇA DE TRABALHO'!$E$15:$E$999, MATCH($L13,'FORÇA DE TRABALHO'!$C$15:$C$999,0), MATCH(O$6+0,'FORÇA DE TRABALHO'!$E$14:$E$14+0,0)), IF( OR(_xlpm.Prod="",_xlpm.Prod=0), IF(_xlpm.Status="ATIVO",0,_xlpm.Status), _xlpm.Prod ) ), "")} -> 4 | P13: {=IFERROR( _xlfn.LET( _xlpm.Prod,INDEX(Din!$J$4:$AR$1000, MATCH($L13,Din!$I$4:$I$1000,0), MATCH(P$6,Din!$J$3:$AO$3,0)), _xlpm.Status,INDEX('FORÇA DE TRABALHO'!$E$15:$E$999, MATCH($L13,'FORÇA DE TRABALHO'!$C$15:$C$999,0), MATCH(P$6+0,'FORÇA DE TRABALHO'!$E$14:$E$14+0,0)), IF( OR(_xlpm.Prod="",_xlpm.Prod=0), IF(_xlpm.Status="ATIVO",0,_xlpm.Status), _xlpm.Prod ) ), "")} -> 2 | Q13: {=IFERROR( _xlfn.LET( _xlpm.Prod,INDEX(Din!$J$4:$AR$1000, MATCH($L13,Din!$I$4:$I$1000,0), MATCH(Q$6,Din!$J$3:$AO$3,0)), _xlpm.Status,INDEX('FORÇA DE TRABALHO'!$E$15:$E$999, MATCH($L13,'FORÇA DE TRABALHO'!$C$15:$C$999,0), MATCH(Q$6+0,'FORÇA DE TRABALHO'!$E$14:$E$14+0,0)), IF( OR(_xlpm.Prod="",_xlpm.Prod=0), IF(_xlpm.Status="ATIVO",0,_xlpm.Status), _xlpm.Prod ) ), "")} | R13: {=IFERROR( _xlfn.LET( _xlpm.Prod,INDEX(Din!$J$4:$AR$1000, MATCH($L13,Din!$I$4:$I$1000,0), MATCH(R$6,Din!$J$3:$AO$3,0)), _xlpm.Status,INDEX('FORÇA DE TRABALHO'!$E$15:$E$999, MATCH($L13,'FORÇA DE TRABALHO'!$C$15:$C$999,0), MATCH(R$6+0,'FORÇA DE TRABALHO'!$E$14:$E$14+0,0)), IF( OR(_xlpm.Prod="",_xlpm.Prod=0), IF(_xlpm.Status="ATIVO",0,_xlpm.Status), _xlpm.Prod ) ), "")} -> 4 | S13: {=IFERROR( _xlfn.LET( _xlpm.Prod,INDEX(Din!$J$4:$AR$1000, MATCH($L13,Din!$I$4:$I$1000,0), MATCH(S$6,Din!$J$3:$AO$3,0)), _xlpm.Status,INDEX('FORÇA DE TRABALHO'!$E$15:$E$999, MATCH($L13,'FORÇA DE TRABALHO'!$C$15:$C$999,0), MATCH(S$6+0,'FORÇA DE TRABALHO'!$E$14:$E$14+0,0)), IF( OR(_xlpm.Prod="",_xlpm.Prod=0), IF(_xlpm.Status="ATIVO",0,_xlpm.Status), _xlpm.Prod ) ), "")} -> 2 | T13: {=IFERROR( _xlfn.LET( _xlpm.Prod,INDEX(Din!$J$4:$AR$1000, MATCH($L13,Din!$I$4:$I$1000,0), MATCH(T$6,Din!$J$3:$AO$3,0)), _xlpm.Status,INDEX('FORÇA DE TRABALHO'!$E$15:$E$999, MATCH($L13,'FORÇA DE TRABALHO'!$C$15:$C$999,0), MATCH(T$6+0,'FORÇA DE TRABALHO'!$E$14:$E$14+0,0)), IF( OR(_xlpm.Prod="",_xlpm.Prod=0), IF(_xlpm.Status="ATIVO",0,_xlpm.Status), _xlpm.Prod ) ), "")} -> 3 | ... AQ13: {=IFERROR( _xlfn.LET( _xlpm.Prod,INDEX(Din!$J$4:$AR$1000, MATCH($L13,Din!$I$4:$I$1000,0), MATCH(AQ$6,Din!$J$3:$AO$3,0)), _xlpm.Status,INDEX('FORÇA DE TRABALHO'!$E$15:$E$999, MATCH($L13,'FORÇA DE TRABALHO'!$C$15:$C$999,0), MATCH(AQ$6+0,'FORÇA DE TRABALHO'!$E$14:$E$14+0,0)), IF( OR(_xlpm.Prod="",_xlpm.Prod=0), IF(_xlpm.Status="ATIVO",0,_xlpm.Status), _xlpm.Prod ) ), "")}
H14: =SUM(M14:AQ14) -> 64 | I14: =ResumoProducao[[#This Row],[Produção]]/ResumoProducao[[#This Row],[Dias Trabalhado]] -> 64 | J14: {=SUMPRODUCT(('FORÇA DE TRABALHO'!$C$15:$C$1007=L14)*('FORÇA DE TRABALHO'!$E$15:$E$1007="ATIVO"))} -> 1 | K14: =IF(I14<2,"4Q",IF(I14<=3,"3Q",IF(I14<=3.9,"2Q","1Q"))) -> 1Q | L14: =IF(Din!A5="","",Din!A5) -> FRANCY ANA ALEXANDRINO CLAUDIO | M14: {=IFERROR( _xlfn.LET( _xlpm.Prod,INDEX(Din!$J$4:$AR$1000, MATCH($L14,Din!$I$4:$I$1000,0), MATCH(M$6,Din!$J$3:$AO$3,0)), _xlpm.Status,INDEX('FORÇA DE TRABALHO'!$E$15:$E$999, MATCH($L14,'FORÇA DE TRABALHO'!$C$15:$C$999,0), MATCH(M$6+0,'FORÇA DE TRABALHO'!$E$14:$E$14+0,0)), IF( OR(_xlpm.Prod="",_xlpm.Prod=0), IF(_xlpm.Status="ATIVO",0,_xlpm.Status), _xlpm.Prod ) ), "")} -> 3 | N14: {=IFERROR( _xlfn.LET( _xlpm.Prod,INDEX(Din!$J$4:$AR$1000, MATCH($L14,Din!$I$4:$I$1000,0), MATCH(N$6,Din!$J$3:$AO$3,0)), _xlpm.Status,INDEX('FORÇA DE TRABALHO'!$E$15:$E$999, MATCH($L14,'FORÇA DE TRABALHO'!$C$15:$C$999,0), MATCH(N$6+0,'FORÇA DE TRABALHO'!$E$14:$E$14+0,0)), IF( OR(_xlpm.Prod="",_xlpm.Prod=0), IF(_xlpm.Status="ATIVO",0,_xlpm.Status), _xlpm.Prod ) ), "")} -> 3 | O14: {=IFERROR( _xlfn.LET( _xlpm.Prod,INDEX(Din!$J$4:$AR$1000, MATCH($L14,Din!$I$4:$I$1000,0), MATCH(O$6,Din!$J$3:$AO$3,0)), _xlpm.Status,INDEX('FORÇA DE TRABALHO'!$E$15:$E$999, MATCH($L14,'FORÇA DE TRABALHO'!$C$15:$C$999,0), MATCH(O$6+0,'FORÇA DE TRABALHO'!$E$14:$E$14+0,0)), IF( OR(_xlpm.Prod="",_xlpm.Prod=0), IF(_xlpm.Status="ATIVO",0,_xlpm.Status), _xlpm.Prod ) ), "")} -> 4 | P14: {=IFERROR( _xlfn.LET( _xlpm.Prod,INDEX(Din!$J$4:$AR$1000, MATCH($L14,Din!$I$4:$I$1000,0), MATCH(P$6,Din!$J$3:$AO$3,0)), _xlpm.Status,INDEX('FORÇA DE TRABALHO'!$E$15:$E$999, MATCH($L14,'FORÇA DE TRABALHO'!$C$15:$C$999,0), MATCH(P$6+0,'FORÇA DE TRABALHO'!$E$14:$E$14+0,0)), IF( OR(_xlpm.Prod="",_xlpm.Prod=0), IF(_xlpm.Status="ATIVO",0,_xlpm.Status), _xlpm.Prod ) ), "")} | Q14: {=IFERROR( _xlfn.LET( _xlpm.Prod,INDEX(Din!$J$4:$AR$1000, MATCH($L14,Din!$I$4:$I$1000,0), MATCH(Q$6,Din!$J$3:$AO$3,0)), _xlpm.Status,INDEX('FORÇA DE TRABALHO'!$E$15:$E$999, MATCH($L14,'FORÇA DE TRABALHO'!$C$15:$C$999,0), MATCH(Q$6+0,'FORÇA DE TRABALHO'!$E$14:$E$14+0,0)), IF( OR(_xlpm.Prod="",_xlpm.Prod=0), IF(_xlpm.Status="ATIVO",0,_xlpm.Status), _xlpm.Prod ) ), "")} | R14: {=IFERROR( _xlfn.LET( _xlpm.Prod,INDEX(Din!$J$4:$AR$1000, MATCH($L14,Din!$I$4:$I$1000,0), MATCH(R$6,Din!$J$3:$AO$3,0)), _xlpm.Status,INDEX('FORÇA DE TRABALHO'!$E$15:$E$999, MATCH($L14,'FORÇA DE TRABALHO'!$C$15:$C$999,0), MATCH(R$6+0,'FORÇA DE TRABALHO'!$E$14:$E$14+0,0)), IF( OR(_xlpm.Prod="",_xlpm.Prod=0), IF(_xlpm.Status="ATIVO",0,_xlpm.Status), _xlpm.Prod ) ), "")} -> 2 | S14: {=IFERROR( _xlfn.LET( _xlpm.Prod,INDEX(Din!$J$4:$AR$1000, MATCH($L14,Din!$I$4:$I$1000,0), MATCH(S$6,Din!$J$3:$AO$3,0)), _xlpm.Status,INDEX('FORÇA DE TRABALHO'!$E$15:$E$999, MATCH($L14,'FORÇA DE TRABALHO'!$C$15:$C$999,0), MATCH(S$6+0,'FORÇA DE TRABALHO'!$E$14:$E$14+0,0)), IF( OR(_xlpm.Prod="",_xlpm.Prod=0), IF(_xlpm.Status="ATIVO",0,_xlpm.Status), _xlpm.Prod ) ), "")} -> 3 | T14: {=IFERROR( _xlfn.LET( _xlpm.Prod,INDEX(Din!$J$4:$AR$1000, MATCH($L14,Din!$I$4:$I$1000,0), MATCH(T$6,Din!$J$3:$AO$3,0)), _xlpm.Status,INDEX('FORÇA DE TRABALHO'!$E$15:$E$999, MATCH($L14,'FORÇA DE TRABALHO'!$C$15:$C$999,0), MATCH(T$6+0,'FORÇA DE TRABALHO'!$E$14:$E$14+0,0)), IF( OR(_xlpm.Prod="",_xlpm.Prod=0), IF(_xlpm.Status="ATIVO",0,_xlpm.Status), _xlpm.Prod ) ), "")} -> 3 | ... AQ14: {=IFERROR( _xlfn.LET( _xlpm.Prod,INDEX(Din!$J$4:$AR$1000, MATCH($L14,Din!$I$4:$I$1000,0), MATCH(AQ$6,Din!$J$3:$AO$3,0)), _xlpm.Status,INDEX('FORÇA DE TRABALHO'!$E$15:$E$999, MATCH($L14,'FORÇA DE TRABALHO'!$C$15:$C$999,0), MATCH(AQ$6+0,'FORÇA DE TRABALHO'!$E$14:$E$14+0,0)), IF( OR(_xlpm.Prod="",_xlpm.Prod=0), IF(_xlpm.Status="ATIVO",0,_xlpm.Status), _xlpm.Prod ) ), "")}
H15: =SUM(M15:AQ15) -> 27 | I15: =ResumoProducao[[#This Row],[Produção]]/ResumoProducao[[#This Row],[Dias Trabalhado]] -> #DIV/0! | J15: {=SUMPRODUCT(('FORÇA DE TRABALHO'!$C$15:$C$1007=L15)*('FORÇA DE TRABALHO'!$E$15:$E$1007="ATIVO"))} -> 0 | K15: =IF(I15<2,"4Q",IF(I15<=3,"3Q",IF(I15<=3.9,"2Q","1Q"))) -> #DIV/0! | L15: =IF(Din!A6="","",Din!A6) -> JAIRON VIEIRA ALVES | M15: {=IFERROR( _xlfn.LET( _xlpm.Prod,INDEX(Din!$J$4:$AR$1000, MATCH($L15,Din!$I$4:$I$1000,0), MATCH(M$6,Din!$J$3:$AO$3,0)), _xlpm.Status,INDEX('FORÇA DE TRABALHO'!$E$15:$E$999, MATCH($L15,'FORÇA DE TRABALHO'!$C$15:$C$999,0), MATCH(M$6+0,'FORÇA DE TRABALHO'!$E$14:$E$14+0,0)), IF( OR(_xlpm.Prod="",_xlpm.Prod=0), IF(_xlpm.Status="ATIVO",0,_xlpm.Status), _xlpm.Prod ) ), "")} -> 3 | N15: {=IFERROR( _xlfn.LET( _xlpm.Prod,INDEX(Din!$J$4:$AR$1000, MATCH($L15,Din!$I$4:$I$1000,0), MATCH(N$6,Din!$J$3:$AO$3,0)), _xlpm.Status,INDEX('FORÇA DE TRABALHO'!$E$15:$E$999, MATCH($L15,'FORÇA DE TRABALHO'!$C$15:$C$999,0), MATCH(N$6+0,'FORÇA DE TRABALHO'!$E$14:$E$14+0,0)), IF( OR(_xlpm.Prod="",_xlpm.Prod=0), IF(_xlpm.Status="ATIVO",0,_xlpm.Status), _xlpm.Prod ) ), "")} -> 2 | O15: {=IFERROR( _xlfn.LET( _xlpm.Prod,INDEX(Din!$J$4:$AR$1000, MATCH($L15,Din!$I$4:$I$1000,0), MATCH(O$6,Din!$J$3:$AO$3,0)), _xlpm.Status,INDEX('FORÇA DE TRABALHO'!$E$15:$E$999, MATCH($L15,'FORÇA DE TRABALHO'!$C$15:$C$999,0), MATCH(O$6+0,'FORÇA DE TRABALHO'!$E$14:$E$14+0,0)), IF( OR(_xlpm.Prod="",_xlpm.Prod=0), IF(_xlpm.Status="ATIVO",0,_xlpm.Status), _xlpm.Prod ) ), "")} -> 4 | P15: {=IFERROR( _xlfn.LET( _xlpm.Prod,INDEX(Din!$J$4:$AR$1000, MATCH($L15,Din!$I$4:$I$1000,0), MATCH(P$6,Din!$J$3:$AO$3,0)), _xlpm.Status,INDEX('FORÇA DE TRABALHO'!$E$15:$E$999, MATCH($L15,'FORÇA DE TRABALHO'!$C$15:$C$999,0), MATCH(P$6+0,'FORÇA DE TRABALHO'!$E$14:$E$14+0,0)), IF( OR(_xlpm.Prod="",_xlpm.Prod=0), IF(_xlpm.Status="ATIVO",0,_xlpm.Status), _xlpm.Prod ) ), "")} -> 1 | Q15: {=IFERROR( _xlfn.LET( _xlpm.Prod,INDEX(Din!$J$4:$AR$1000, MATCH($L15,Din!$I$4:$I$1000,0), MATCH(Q$6,Din!$J$3:$AO$3,0)), _xlpm.Status,INDEX('FORÇA DE TRABALHO'!$E$15:$E$999, MATCH($L15,'FORÇA DE TRABALHO'!$C$15:$C$999,0), MATCH(Q$6+0,'FORÇA DE TRABALHO'!$E$14:$E$14+0,0)), IF( OR(_xlpm.Prod="",_xlpm.Prod=0), IF(_xlpm.Status="ATIVO",0,_xlpm.Status), _xlpm.Prod ) ), "")} -> 5 | R15: {=IFERROR( _xlfn.LET( _xlpm.Prod,INDEX(Din!$J$4:$AR$1000, MATCH($L15,Din!$I$4:$I$1000,0), MATCH(R$6,Din!$J$3:$AO$3,0)), _xlpm.Status,INDEX('FORÇA DE TRABALHO'!$E$15:$E$999, MATCH($L15,'FORÇA DE TRABALHO'!$C$15:$C$999,0), MATCH(R$6+0,'FORÇA DE TRABALHO'!$E$14:$E$14+0,0)), IF( OR(_xlpm.Prod="",_xlpm.Prod=0), IF(_xlpm.Status="ATIVO",0,_xlpm.Status), _xlpm.Prod ) ), "")} -> 2 | S15: {=IFERROR( _xlfn.LET( _xlpm.Prod,INDEX(Din!$J$4:$AR$1000, MATCH($L15,Din!$I$4:$I$1000,0), MATCH(S$6,Din!$J$3:$AO$3,0)), _xlpm.Status,INDEX('FORÇA DE TRABALHO'!$E$15:$E$999, MATCH($L15,'FORÇA DE TRABALHO'!$C$15:$C$999,0), MATCH(S$6+0,'FORÇA DE TRABALHO'!$E$14:$E$14+0,0)), IF( OR(_xlpm.Prod="",_xlpm.Prod=0), IF(_xlpm.Status="ATIVO",0,_xlpm.Status), _xlpm.Prod ) ), "")} -> 3 | T15: {=IFERROR( _xlfn.LET( _xlpm.Prod,INDEX(Din!$J$4:$AR$1000, MATCH($L15,Din!$I$4:$I$1000,0), MATCH(T$6,Din!$J$3:$AO$3,0)), _xlpm.Status,INDEX('FORÇA DE TRABALHO'!$E$15:$E$999, MATCH($L15,'FORÇA DE TRABALHO'!$C$15:$C$999,0), MATCH(T$6+0,'FORÇA DE TRABALHO'!$E$14:$E$14+0,0)), IF( OR(_xlpm.Prod="",_xlpm.Prod=0), IF(_xlpm.Status="ATIVO",0,_xlpm.Status), _xlpm.Prod ) ), "")} -> 5 | ... AQ15: {=IFERROR( _xlfn.LET( _xlpm.Prod,INDEX(Din!$J$4:$AR$1000, MATCH($L15,Din!$I$4:$I$1000,0), MATCH(AQ$6,Din!$J$3:$AO$3,0)), _xlpm.Status,INDEX('FORÇA DE TRABALHO'!$E$15:$E$999, MATCH($L15,'FORÇA DE TRABALHO'!$C$15:$C$999,0), MATCH(AQ$6+0,'FORÇA DE TRABALHO'!$E$14:$E$14+0,0)), IF( OR(_xlpm.Prod="",_xlpm.Prod=0), IF(_xlpm.Status="ATIVO",0,_xlpm.Status), _xlpm.Prod ) ), "")}
H16: =SUM(M16:AQ16) -> 59 | I16: =ResumoProducao[[#This Row],[Produção]]/ResumoProducao[[#This Row],[Dias Trabalhado]] -> 59 | J16: {=SUMPRODUCT(('FORÇA DE TRABALHO'!$C$15:$C$1007=L16)*('FORÇA DE TRABALHO'!$E$15:$E$1007="ATIVO"))} -> 1 | K16: =IF(I16<2,"4Q",IF(I16<=3,"3Q",IF(I16<=3.9,"2Q","1Q"))) -> 1Q | L16: =IF(Din!A7="","",Din!A7) -> FERNANDO PINHEIRO DA SILVA JUNIOR | M16: {=IFERROR( _xlfn.LET( _xlpm.Prod,INDEX(Din!$J$4:$AR$1000, MATCH($L16,Din!$I$4:$I$1000,0), MATCH(M$6,Din!$J$3:$AO$3,0)), _xlpm.Status,INDEX('FORÇA DE TRABALHO'!$E$15:$E$999, MATCH($L16,'FORÇA DE TRABALHO'!$C$15:$C$999,0), MATCH(M$6+0,'FORÇA DE TRABALHO'!$E$14:$E$14+0,0)), IF( OR(_xlpm.Prod="",_xlpm.Prod=0), IF(_xlpm.Status="ATIVO",0,_xlpm.Status), _xlpm.Prod ) ), "")} -> 3 | N16: {=IFERROR( _xlfn.LET( _xlpm.Prod,INDEX(Din!$J$4:$AR$1000, MATCH($L16,Din!$I$4:$I$1000,0), MATCH(N$6,Din!$J$3:$AO$3,0)), _xlpm.Status,INDEX('FORÇA DE TRABALHO'!$E$15:$E$999, MATCH($L16,'FORÇA DE TRABALHO'!$C$15:$C$999,0), MATCH(N$6+0,'FORÇA DE TRABALHO'!$E$14:$E$14+0,0)), IF( OR(_xlpm.Prod="",_xlpm.Prod=0), IF(_xlpm.Status="ATIVO",0,_xlpm.Status), _xlpm.Prod ) ), "")} -> 4 | O16: {=IFERROR( _xlfn.LET( _xlpm.Prod,INDEX(Din!$J$4:$AR$1000, MATCH($L16,Din!$I$4:$I$1000,0), MATCH(O$6,Din!$J$3:$AO$3,0)), _xlpm.Status,INDEX('FORÇA DE TRABALHO'!$E$15:$E$999, MATCH($L16,'FORÇA DE TRABALHO'!$C$15:$C$999,0), MATCH(O$6+0,'FORÇA DE TRABALHO'!$E$14:$E$14+0,0)), IF( OR(_xlpm.Prod="",_xlpm.Prod=0), IF(_xlpm.Status="ATIVO",0,_xlpm.Status), _xlpm.Prod ) ), "")} -> 3 | P16: {=IFERROR( _xlfn.LET( _xlpm.Prod,INDEX(Din!$J$4:$AR$1000, MATCH($L16,Din!$I$4:$I$1000,0), MATCH(P$6,Din!$J$3:$AO$3,0)), _xlpm.Status,INDEX('FORÇA DE TRABALHO'!$E$15:$E$999, MATCH($L16,'FORÇA DE TRABALHO'!$C$15:$C$999,0), MATCH(P$6+0,'FORÇA DE TRABALHO'!$E$14:$E$14+0,0)), IF( OR(_xlpm.Prod="",_xlpm.Prod=0), IF(_xlpm.Status="ATIVO",0,_xlpm.Status), _xlpm.Prod ) ), "")} -> 4 | Q16: {=IFERROR( _xlfn.LET( _xlpm.Prod,INDEX(Din!$J$4:$AR$1000, MATCH($L16,Din!$I$4:$I$1000,0), MATCH(Q$6,Din!$J$3:$AO$3,0)), _xlpm.Status,INDEX('FORÇA DE TRABALHO'!$E$15:$E$999, MATCH($L16,'FORÇA DE TRABALHO'!$C$15:$C$999,0), MATCH(Q$6+0,'FORÇA DE TRABALHO'!$E$14:$E$14+0,0)), IF( OR(_xlpm.Prod="",_xlpm.Prod=0), IF(_xlpm.Status="ATIVO",0,_xlpm.Status), _xlpm.Prod ) ), "")} | R16: {=IFERROR( _xlfn.LET( _xlpm.Prod,INDEX(Din!$J$4:$AR$1000, MATCH($L16,Din!$I$4:$I$1000,0), MATCH(R$6,Din!$J$3:$AO$3,0)), _xlpm.Status,INDEX('FORÇA DE TRABALHO'!$E$15:$E$999, MATCH($L16,'FORÇA DE TRABALHO'!$C$15:$C$999,0), MATCH(R$6+0,'FORÇA DE TRABALHO'!$E$14:$E$14+0,0)), IF( OR(_xlpm.Prod="",_xlpm.Prod=0), IF(_xlpm.Status="ATIVO",0,_xlpm.Status), _xlpm.Prod ) ), "")} -> 5 | S16: {=IFERROR( _xlfn.LET( _xlpm.Prod,INDEX(Din!$J$4:$AR$1000, MATCH($L16,Din!$I$4:$I$1000,0), MATCH(S$6,Din!$J$3:$AO$3,0)), _xlpm.Status,INDEX('FORÇA DE TRABALHO'!$E$15:$E$999, MATCH($L16,'FORÇA DE TRABALHO'!$C$15:$C$999,0), MATCH(S$6+0,'FORÇA DE TRABALHO'!$E$14:$E$14+0,0)), IF( OR(_xlpm.Prod="",_xlpm.Prod=0), IF(_xlpm.Status="ATIVO",0,_xlpm.Status), _xlpm.Prod ) ), "")} -> 2 | T16: {=IFERROR( _xlfn.LET( _xlpm.Prod,INDEX(Din!$J$4:$AR$1000, MATCH($L16,Din!$I$4:$I$1000,0), MATCH(T$6,Din!$J$3:$AO$3,0)), _xlpm.Status,INDEX('FORÇA DE TRABALHO'!$E$15:$E$999, MATCH($L16,'FORÇA DE TRABALHO'!$C$15:$C$999,0), MATCH(T$6+0,'FORÇA DE TRABALHO'!$E$14:$E$14+0,0)), IF( OR(_xlpm.Prod="",_xlpm.Prod=0), IF(_xlpm.Status="ATIVO",0,_xlpm.Status), _xlpm.Prod ) ), "")} -> 2 | ... AQ16: {=IFERROR( _xlfn.LET( _xlpm.Prod,INDEX(Din!$J$4:$AR$1000, MATCH($L16,Din!$I$4:$I$1000,0), MATCH(AQ$6,Din!$J$3:$AO$3,0)), _xlpm.Status,INDEX('FORÇA DE TRABALHO'!$E$15:$E$999, MATCH($L16,'FORÇA DE TRABALHO'!$C$15:$C$999,0), MATCH(AQ$6+0,'FORÇA DE TRABALHO'!$E$14:$E$14+0,0)), IF( OR(_xlpm.Prod="",_xlpm.Prod=0), IF(_xlpm.Status="ATIVO",0,_xlpm.Status), _xlpm.Prod ) ), "")}
H17: =SUM(M17:AQ17) -> 58 | I17: =ResumoProducao[[#This Row],[Produção]]/ResumoProducao[[#This Row],[Dias Trabalhado]] -> 58 | J17: {=SUMPRODUCT(('FORÇA DE TRABALHO'!$C$15:$C$1007=L17)*('FORÇA DE TRABALHO'!$E$15:$E$1007="ATIVO"))} -> 1 | K17: =IF(I17<2,"4Q",IF(I17<=3,"3Q",IF(I17<=3.9,"2Q","1Q"))) -> 1Q | L17: =IF(Din!A8="","",Din!A8) -> EDSON TAVARES DA SILVA JUNIOR | M17: {=IFERROR( _xlfn.LET( _xlpm.Prod,INDEX(Din!$J$4:$AR$1000, MATCH($L17,Din!$I$4:$I$1000,0), MATCH(M$6,Din!$J$3:$AO$3,0)), _xlpm.Status,INDEX('FORÇA DE TRABALHO'!$E$15:$E$999, MATCH($L17,'FORÇA DE TRABALHO'!$C$15:$C$999,0), MATCH(M$6+0,'FORÇA DE TRABALHO'!$E$14:$E$14+0,0)), IF( OR(_xlpm.Prod="",_xlpm.Prod=0), IF(_xlpm.Status="ATIVO",0,_xlpm.Status), _xlpm.Prod ) ), "")} -> 3 | N17: {=IFERROR( _xlfn.LET( _xlpm.Prod,INDEX(Din!$J$4:$AR$1000, MATCH($L17,Din!$I$4:$I$1000,0), MATCH(N$6,Din!$J$3:$AO$3,0)), _xlpm.Status,INDEX('FORÇA DE TRABALHO'!$E$15:$E$999, MATCH($L17,'FORÇA DE TRABALHO'!$C$15:$C$999,0), MATCH(N$6+0,'FORÇA DE TRABALHO'!$E$14:$E$14+0,0)), IF( OR(_xlpm.Prod="",_xlpm.Prod=0), IF(_xlpm.Status="ATIVO",0,_xlpm.Status), _xlpm.Prod ) ), "")} -> 4 | O17: {=IFERROR( _xlfn.LET( _xlpm.Prod,INDEX(Din!$J$4:$AR$1000, MATCH($L17,Din!$I$4:$I$1000,0), MATCH(O$6,Din!$J$3:$AO$3,0)), _xlpm.Status,INDEX('FORÇA DE TRABALHO'!$E$15:$E$999, MATCH($L17,'FORÇA DE TRABALHO'!$C$15:$C$999,0), MATCH(O$6+0,'FORÇA DE TRABALHO'!$E$14:$E$14+0,0)), IF( OR(_xlpm.Prod="",_xlpm.Prod=0), IF(_xlpm.Status="ATIVO",0,_xlpm.Status), _xlpm.Prod ) ), "")} -> 4 | P17: {=IFERROR( _xlfn.LET( _xlpm.Prod,INDEX(Din!$J$4:$AR$1000, MATCH($L17,Din!$I$4:$I$1000,0), MATCH(P$6,Din!$J$3:$AO$3,0)), _xlpm.Status,INDEX('FORÇA DE TRABALHO'!$E$15:$E$999, MATCH($L17,'FORÇA DE TRABALHO'!$C$15:$C$999,0), MATCH(P$6+0,'FORÇA DE TRABALHO'!$E$14:$E$14+0,0)), IF( OR(_xlpm.Prod="",_xlpm.Prod=0), IF(_xlpm.Status="ATIVO",0,_xlpm.Status), _xlpm.Prod ) ), "")} -> 4 | Q17: {=IFERROR( _xlfn.LET( _xlpm.Prod,INDEX(Din!$J$4:$AR$1000, MATCH($L17,Din!$I$4:$I$1000,0), MATCH(Q$6,Din!$J$3:$AO$3,0)), _xlpm.Status,INDEX('FORÇA DE TRABALHO'!$E$15:$E$999, MATCH($L17,'FORÇA DE TRABALHO'!$C$15:$C$999,0), MATCH(Q$6+0,'FORÇA DE TRABALHO'!$E$14:$E$14+0,0)), IF( OR(_xlpm.Prod="",_xlpm.Prod=0), IF(_xlpm.Status="ATIVO",0,_xlpm.Status), _xlpm.Prod ) ), "")} | R17: {=IFERROR( _xlfn.LET( _xlpm.Prod,INDEX(Din!$J$4:$AR$1000, MATCH($L17,Din!$I$4:$I$1000,0), MATCH(R$6,Din!$J$3:$AO$3,0)), _xlpm.Status,INDEX('FORÇA DE TRABALHO'!$E$15:$E$999, MATCH($L17,'FORÇA DE TRABALHO'!$C$15:$C$999,0), MATCH(R$6+0,'FORÇA DE TRABALHO'!$E$14:$E$14+0,0)), IF( OR(_xlpm.Prod="",_xlpm.Prod=0), IF(_xlpm.Status="ATIVO",0,_xlpm.Status), _xlpm.Prod ) ), "")} -> 5 | S17: {=IFERROR( _xlfn.LET( _xlpm.Prod,INDEX(Din!$J$4:$AR$1000, MATCH($L17,Din!$I$4:$I$1000,0), MATCH(S$6,Din!$J$3:$AO$3,0)), _xlpm.Status,INDEX('FORÇA DE TRABALHO'!$E$15:$E$999, MATCH($L17,'FORÇA DE TRABALHO'!$C$15:$C$999,0), MATCH(S$6+0,'FORÇA DE TRABALHO'!$E$14:$E$14+0,0)), IF( OR(_xlpm.Prod="",_xlpm.Prod=0), IF(_xlpm.Status="ATIVO",0,_xlpm.Status), _xlpm.Prod ) ), "")} -> 2 | T17: {=IFERROR( _xlfn.LET( _xlpm.Prod,INDEX(Din!$J$4:$AR$1000, MATCH($L17,Din!$I$4:$I$1000,0), MATCH(T$6,Din!$J$3:$AO$3,0)), _xlpm.Status,INDEX('FORÇA DE TRABALHO'!$E$15:$E$999, MATCH($L17,'FORÇA DE TRABALHO'!$C$15:$C$999,0), MATCH(T$6+0,'FORÇA DE TRABALHO'!$E$14:$E$14+0,0)), IF( OR(_xlpm.Prod="",_xlpm.Prod=0), IF(_xlpm.Status="ATIVO",0,_xlpm.Status), _xlpm.Prod ) ), "")} -> 2 | ... AQ17: {=IFERROR( _xlfn.LET( _xlpm.Prod,INDEX(Din!$J$4:$AR$1000, MATCH($L17,Din!$I$4:$I$1000,0), MATCH(AQ$6,Din!$J$3:$AO$3,0)), _xlpm.Status,INDEX('FORÇA DE TRABALHO'!$E$15:$E$999, MATCH($L17,'FORÇA DE TRABALHO'!$C$15:$C$999,0), MATCH(AQ$6+0,'FORÇA DE TRABALHO'!$E$14:$E$14+0,0)), IF( OR(_xlpm.Prod="",_xlpm.Prod=0), IF(_xlpm.Status="ATIVO",0,_xlpm.Status), _xlpm.Prod ) ), "")}
H18: =SUM(M18:AQ18) -> 54 | I18: =ResumoProducao[[#This Row],[Produção]]/ResumoProducao[[#This Row],[Dias Trabalhado]] -> 54 | J18: {=SUMPRODUCT(('FORÇA DE TRABALHO'!$C$15:$C$1007=L18)*('FORÇA DE TRABALHO'!$E$15:$E$1007="ATIVO"))} -> 1 | K18: =IF(I18<2,"4Q",IF(I18<=3,"3Q",IF(I18<=3.9,"2Q","1Q"))) -> 1Q | L18: =IF(Din!A9="","",Din!A9) -> HELIO SANDRO MONTEIRO PEIXOTO | M18: {=IFERROR( _xlfn.LET( _xlpm.Prod,INDEX(Din!$J$4:$AR$1000, MATCH($L18,Din!$I$4:$I$1000,0), MATCH(M$6,Din!$J$3:$AO$3,0)), _xlpm.Status,INDEX('FORÇA DE TRABALHO'!$E$15:$E$999, MATCH($L18,'FORÇA DE TRABALHO'!$C$15:$C$999,0), MATCH(M$6+0,'FORÇA DE TRABALHO'!$E$14:$E$14+0,0)), IF( OR(_xlpm.Prod="",_xlpm.Prod=0), IF(_xlpm.Status="ATIVO",0,_xlpm.Status), _xlpm.Prod ) ), "")} -> 1 | N18: {=IFERROR( _xlfn.LET( _xlpm.Prod,INDEX(Din!$J$4:$AR$1000, MATCH($L18,Din!$I$4:$I$1000,0), MATCH(N$6,Din!$J$3:$AO$3,0)), _xlpm.Status,INDEX('FORÇA DE TRABALHO'!$E$15:$E$999, MATCH($L18,'FORÇA DE TRABALHO'!$C$15:$C$999,0), MATCH(N$6+0,'FORÇA DE TRABALHO'!$E$14:$E$14+0,0)), IF( OR(_xlpm.Prod="",_xlpm.Prod=0), IF(_xlpm.Status="ATIVO",0,_xlpm.Status), _xlpm.Prod ) ), "")} -> 4 | O18: {=IFERROR( _xlfn.LET( _xlpm.Prod,INDEX(Din!$J$4:$AR$1000, MATCH($L18,Din!$I$4:$I$1000,0), MATCH(O$6,Din!$J$3:$AO$3,0)), _xlpm.Status,INDEX('FORÇA DE TRABALHO'!$E$15:$E$999, MATCH($L18,'FORÇA DE TRABALHO'!$C$15:$C$999,0), MATCH(O$6+0,'FORÇA DE TRABALHO'!$E$14:$E$14+0,0)), IF( OR(_xlpm.Prod="",_xlpm.Prod=0), IF(_xlpm.Status="ATIVO",0,_xlpm.Status), _xlpm.Prod ) ), "")} -> 3 | P18: {=IFERROR( _xlfn.LET( _xlpm.Prod,INDEX(Din!$J$4:$AR$1000, MATCH($L18,Din!$I$4:$I$1000,0), MATCH(P$6,Din!$J$3:$AO$3,0)), _xlpm.Status,INDEX('FORÇA DE TRABALHO'!$E$15:$E$999, MATCH($L18,'FORÇA DE TRABALHO'!$C$15:$C$999,0), MATCH(P$6+0,'FORÇA DE TRABALHO'!$E$14:$E$14+0,0)), IF( OR(_xlpm.Prod="",_xlpm.Prod=0), IF(_xlpm.Status="ATIVO",0,_xlpm.Status), _xlpm.Prod ) ), "")} -> 1 | Q18: {=IFERROR( _xlfn.LET( _xlpm.Prod,INDEX(Din!$J$4:$AR$1000, MATCH($L18,Din!$I$4:$I$1000,0), MATCH(Q$6,Din!$J$3:$AO$3,0)), _xlpm.Status,INDEX('FORÇA DE TRABALHO'!$E$15:$E$999, MATCH($L18,'FORÇA DE TRABALHO'!$C$15:$C$999,0), MATCH(Q$6+0,'FORÇA DE TRABALHO'!$E$14:$E$14+0,0)), IF( OR(_xlpm.Prod="",_xlpm.Prod=0), IF(_xlpm.Status="ATIVO",0,_xlpm.Status), _xlpm.Prod ) ), "")} | R18: {=IFERROR( _xlfn.LET( _xlpm.Prod,INDEX(Din!$J$4:$AR$1000, MATCH($L18,Din!$I$4:$I$1000,0), MATCH(R$6,Din!$J$3:$AO$3,0)), _xlpm.Status,INDEX('FORÇA DE TRABALHO'!$E$15:$E$999, MATCH($L18,'FORÇA DE TRABALHO'!$C$15:$C$999,0), MATCH(R$6+0,'FORÇA DE TRABALHO'!$E$14:$E$14+0,0)), IF( OR(_xlpm.Prod="",_xlpm.Prod=0), IF(_xlpm.Status="ATIVO",0,_xlpm.Status), _xlpm.Prod ) ), "")} -> 3 | S18: {=IFERROR( _xlfn.LET( _xlpm.Prod,INDEX(Din!$J$4:$AR$1000, MATCH($L18,Din!$I$4:$I$1000,0), MATCH(S$6,Din!$J$3:$AO$3,0)), _xlpm.Status,INDEX('FORÇA DE TRABALHO'!$E$15:$E$999, MATCH($L18,'FORÇA DE TRABALHO'!$C$15:$C$999,0), MATCH(S$6+0,'FORÇA DE TRABALHO'!$E$14:$E$14+0,0)), IF( OR(_xlpm.Prod="",_xlpm.Prod=0), IF(_xlpm.Status="ATIVO",0,_xlpm.Status), _xlpm.Prod ) ), "")} -> 2 | T18: {=IFERROR( _xlfn.LET( _xlpm.Prod,INDEX(Din!$J$4:$AR$1000, MATCH($L18,Din!$I$4:$I$1000,0), MATCH(T$6,Din!$J$3:$AO$3,0)), _xlpm.Status,INDEX('FORÇA DE TRABALHO'!$E$15:$E$999, MATCH($L18,'FORÇA DE TRABALHO'!$C$15:$C$999,0), MATCH(T$6+0,'FORÇA DE TRABALHO'!$E$14:$E$14+0,0)), IF( OR(_xlpm.Prod="",_xlpm.Prod=0), IF(_xlpm.Status="ATIVO",0,_xlpm.Status), _xlpm.Prod ) ), "")} -> 1 | ... AQ18: {=IFERROR( _xlfn.LET( _xlpm.Prod,INDEX(Din!$J$4:$AR$1000, MATCH($L18,Din!$I$4:$I$1000,0), MATCH(AQ$6,Din!$J$3:$AO$3,0)), _xlpm.Status,INDEX('FORÇA DE TRABALHO'!$E$15:$E$999, MATCH($L18,'FORÇA DE TRABALHO'!$C$15:$C$999,0), MATCH(AQ$6+0,'FORÇA DE TRABALHO'!$E$14:$E$14+0,0)), IF( OR(_xlpm.Prod="",_xlpm.Prod=0), IF(_xlpm.Status="ATIVO",0,_xlpm.Status), _xlpm.Prod ) ), "")}
H19: =SUM(M19:AQ19) -> 46 | I19: =ResumoProducao[[#This Row],[Produção]]/ResumoProducao[[#This Row],[Dias Trabalhado]] -> 46 | J19: {=SUMPRODUCT(('FORÇA DE TRABALHO'!$C$15:$C$1007=L19)*('FORÇA DE TRABALHO'!$E$15:$E$1007="ATIVO"))} -> 1 | K19: =IF(I19<2,"4Q",IF(I19<=3,"3Q",IF(I19<=3.9,"2Q","1Q"))) -> 1Q | L19: =IF(Din!A10="","",Din!A10) -> PAULO ROBERTO DA SILVA | M19: {=IFERROR( _xlfn.LET( _xlpm.Prod,INDEX(Din!$J$4:$AR$1000, MATCH($L19,Din!$I$4:$I$1000,0), MATCH(M$6,Din!$J$3:$AO$3,0)), _xlpm.Status,INDEX('FORÇA DE TRABALHO'!$E$15:$E$999, MATCH($L19,'FORÇA DE TRABALHO'!$C$15:$C$999,0), MATCH(M$6+0,'FORÇA DE TRABALHO'!$E$14:$E$14+0,0)), IF( OR(_xlpm.Prod="",_xlpm.Prod=0), IF(_xlpm.Status="ATIVO",0,_xlpm.Status), _xlpm.Prod ) ), "")} -> 1 | N19: {=IFERROR( _xlfn.LET( _xlpm.Prod,INDEX(Din!$J$4:$AR$1000, MATCH($L19,Din!$I$4:$I$1000,0), MATCH(N$6,Din!$J$3:$AO$3,0)), _xlpm.Status,INDEX('FORÇA DE TRABALHO'!$E$15:$E$999, MATCH($L19,'FORÇA DE TRABALHO'!$C$15:$C$999,0), MATCH(N$6+0,'FORÇA DE TRABALHO'!$E$14:$E$14+0,0)), IF( OR(_xlpm.Prod="",_xlpm.Prod=0), IF(_xlpm.Status="ATIVO",0,_xlpm.Status), _xlpm.Prod ) ), "")} -> 1 | O19: {=IFERROR( _xlfn.LET( _xlpm.Prod,INDEX(Din!$J$4:$AR$1000, MATCH($L19,Din!$I$4:$I$1000,0), MATCH(O$6,Din!$J$3:$AO$3,0)), _xlpm.Status,INDEX('FORÇA DE TRABALHO'!$E$15:$E$999, MATCH($L19,'FORÇA DE TRABALHO'!$C$15:$C$999,0), MATCH(O$6+0,'FORÇA DE TRABALHO'!$E$14:$E$14+0,0)), IF( OR(_xlpm.Prod="",_xlpm.Prod=0), IF(_xlpm.Status="ATIVO",0,_xlpm.Status), _xlpm.Prod ) ), "")} -> 1 | P19: {=IFERROR( _xlfn.LET( _xlpm.Prod,INDEX(Din!$J$4:$AR$1000, MATCH($L19,Din!$I$4:$I$1000,0), MATCH(P$6,Din!$J$3:$AO$3,0)), _xlpm.Status,INDEX('FORÇA DE TRABALHO'!$E$15:$E$999, MATCH($L19,'FORÇA DE TRABALHO'!$C$15:$C$999,0), MATCH(P$6+0,'FORÇA DE TRABALHO'!$E$14:$E$14+0,0)), IF( OR(_xlpm.Prod="",_xlpm.Prod=0), IF(_xlpm.Status="ATIVO",0,_xlpm.Status), _xlpm.Prod ) ), "")} -> 2 | Q19: {=IFERROR( _xlfn.LET( _xlpm.Prod,INDEX(Din!$J$4:$AR$1000, MATCH($L19,Din!$I$4:$I$1000,0), MATCH(Q$6,Din!$J$3:$AO$3,0)), _xlpm.Status,INDEX('FORÇA DE TRABALHO'!$E$15:$E$999, MATCH($L19,'FORÇA DE TRABALHO'!$C$15:$C$999,0), MATCH(Q$6+0,'FORÇA DE TRABALHO'!$E$14:$E$14+0,0)), IF( OR(_xlpm.Prod="",_xlpm.Prod=0), IF(_xlpm.Status="ATIVO",0,_xlpm.Status), _xlpm.Prod ) ), "")} | R19: {=IFERROR( _xlfn.LET( _xlpm.Prod,INDEX(Din!$J$4:$AR$1000, MATCH($L19,Din!$I$4:$I$1000,0), MATCH(R$6,Din!$J$3:$AO$3,0)), _xlpm.Status,INDEX('FORÇA DE TRABALHO'!$E$15:$E$999, MATCH($L19,'FORÇA DE TRABALHO'!$C$15:$C$999,0), MATCH(R$6+0,'FORÇA DE TRABALHO'!$E$14:$E$14+0,0)), IF( OR(_xlpm.Prod="",_xlpm.Prod=0), IF(_xlpm.Status="ATIVO",0,_xlpm.Status), _xlpm.Prod ) ), "")} -> 1 | S19: {=IFERROR( _xlfn.LET( _xlpm.Prod,INDEX(Din!$J$4:$AR$1000, MATCH($L19,Din!$I$4:$I$1000,0), MATCH(S$6,Din!$J$3:$AO$3,0)), _xlpm.Status,INDEX('FORÇA DE TRABALHO'!$E$15:$E$999, MATCH($L19,'FORÇA DE TRABALHO'!$C$15:$C$999,0), MATCH(S$6+0,'FORÇA DE TRABALHO'!$E$14:$E$14+0,0)), IF( OR(_xlpm.Prod="",_xlpm.Prod=0), IF(_xlpm.Status="ATIVO",0,_xlpm.Status), _xlpm.Prod ) ), "")} -> 3 | T19: {=IFERROR( _xlfn.LET( _xlpm.Prod,INDEX(Din!$J$4:$AR$1000, MATCH($L19,Din!$I$4:$I$1000,0), MATCH(T$6,Din!$J$3:$AO$3,0)), _xlpm.Status,INDEX('FORÇA DE TRABALHO'!$E$15:$E$999, MATCH($L19,'FORÇA DE TRABALHO'!$C$15:$C$999,0), MATCH(T$6+0,'FORÇA DE TRABALHO'!$E$14:$E$14+0,0)), IF( OR(_xlpm.Prod="",_xlpm.Prod=0), IF(_xlpm.Status="ATIVO",0,_xlpm.Status), _xlpm.Prod ) ), "")} -> 3 | ... AQ19: {=IFERROR( _xlfn.LET( _xlpm.Prod,INDEX(Din!$J$4:$AR$1000, MATCH($L19,Din!$I$4:$I$1000,0), MATCH(AQ$6,Din!$J$3:$AO$3,0)), _xlpm.Status,INDEX('FORÇA DE TRABALHO'!$E$15:$E$999, MATCH($L19,'FORÇA DE TRABALHO'!$C$15:$C$999,0), MATCH(AQ$6+0,'FORÇA DE TRABALHO'!$E$14:$E$14+0,0)), IF( OR(_xlpm.Prod="",_xlpm.Prod=0), IF(_xlpm.Status="ATIVO",0,_xlpm.Status), _xlpm.Prod ) ), "")}
H20: =SUM(M20:AQ20) -> 39 | I20: =ResumoProducao[[#This Row],[Produção]]/ResumoProducao[[#This Row],[Dias Trabalhado]] -> 39 | J20: {=SUMPRODUCT(('FORÇA DE TRABALHO'!$C$15:$C$1007=L20)*('FORÇA DE TRABALHO'!$E$15:$E$1007="ATIVO"))} -> 1 | K20: =IF(I20<2,"4Q",IF(I20<=3,"3Q",IF(I20<=3.9,"2Q","1Q"))) -> 1Q | L20: =IF(Din!A11="","",Din!A11) -> CARLOS EDUARDO DA SILVA | M20: {=IFERROR( _xlfn.LET( _xlpm.Prod,INDEX(Din!$J$4:$AR$1000, MATCH($L20,Din!$I$4:$I$1000,0), MATCH(M$6,Din!$J$3:$AO$3,0)), _xlpm.Status,INDEX('FORÇA DE TRABALHO'!$E$15:$E$999, MATCH($L20,'FORÇA DE TRABALHO'!$C$15:$C$999,0), MATCH(M$6+0,'FORÇA DE TRABALHO'!$E$14:$E$14+0,0)), IF( OR(_xlpm.Prod="",_xlpm.Prod=0), IF(_xlpm.Status="ATIVO",0,_xlpm.Status), _xlpm.Prod ) ), "")} | N20: {=IFERROR( _xlfn.LET( _xlpm.Prod,INDEX(Din!$J$4:$AR$1000, MATCH($L20,Din!$I$4:$I$1000,0), MATCH(N$6,Din!$J$3:$AO$3,0)), _xlpm.Status,INDEX('FORÇA DE TRABALHO'!$E$15:$E$999, MATCH($L20,'FORÇA DE TRABALHO'!$C$15:$C$999,0), MATCH(N$6+0,'FORÇA DE TRABALHO'!$E$14:$E$14+0,0)), IF( OR(_xlpm.Prod="",_xlpm.Prod=0), IF(_xlpm.Status="ATIVO",0,_xlpm.Status), _xlpm.Prod ) ), "")} | O20: {=IFERROR( _xlfn.LET( _xlpm.Prod,INDEX(Din!$J$4:$AR$1000, MATCH($L20,Din!$I$4:$I$1000,0), MATCH(O$6,Din!$J$3:$AO$3,0)), _xlpm.Status,INDEX('FORÇA DE TRABALHO'!$E$15:$E$999, MATCH($L20,'FORÇA DE TRABALHO'!$C$15:$C$999,0), MATCH(O$6+0,'FORÇA DE TRABALHO'!$E$14:$E$14+0,0)), IF( OR(_xlpm.Prod="",_xlpm.Prod=0), IF(_xlpm.Status="ATIVO",0,_xlpm.Status), _xlpm.Prod ) ), "")} | P20: {=IFERROR( _xlfn.LET( _xlpm.Prod,INDEX(Din!$J$4:$AR$1000, MATCH($L20,Din!$I$4:$I$1000,0), MATCH(P$6,Din!$J$3:$AO$3,0)), _xlpm.Status,INDEX('FORÇA DE TRABALHO'!$E$15:$E$999, MATCH($L20,'FORÇA DE TRABALHO'!$C$15:$C$999,0), MATCH(P$6+0,'FORÇA DE TRABALHO'!$E$14:$E$14+0,0)), IF( OR(_xlpm.Prod="",_xlpm.Prod=0), IF(_xlpm.Status="ATIVO",0,_xlpm.Status), _xlpm.Prod ) ), "")} | Q20: {=IFERROR( _xlfn.LET( _xlpm.Prod,INDEX(Din!$J$4:$AR$1000, MATCH($L20,Din!$I$4:$I$1000,0), MATCH(Q$6,Din!$J$3:$AO$3,0)), _xlpm.Status,INDEX('FORÇA DE TRABALHO'!$E$15:$E$999, MATCH($L20,'FORÇA DE TRABALHO'!$C$15:$C$999,0), MATCH(Q$6+0,'FORÇA DE TRABALHO'!$E$14:$E$14+0,0)), IF( OR(_xlpm.Prod="",_xlpm.Prod=0), IF(_xlpm.Status="ATIVO",0,_xlpm.Status), _xlpm.Prod ) ), "")} | R20: {=IFERROR( _xlfn.LET( _xlpm.Prod,INDEX(Din!$J$4:$AR$1000, MATCH($L20,Din!$I$4:$I$1000,0), MATCH(R$6,Din!$J$3:$AO$3,0)), _xlpm.Status,INDEX('FORÇA DE TRABALHO'!$E$15:$E$999, MATCH($L20,'FORÇA DE TRABALHO'!$C$15:$C$999,0), MATCH(R$6+0,'FORÇA DE TRABALHO'!$E$14:$E$14+0,0)), IF( OR(_xlpm.Prod="",_xlpm.Prod=0), IF(_xlpm.Status="ATIVO",0,_xlpm.Status), _xlpm.Prod ) ), "")} -> 2 | S20: {=IFERROR( _xlfn.LET( _xlpm.Prod,INDEX(Din!$J$4:$AR$1000, MATCH($L20,Din!$I$4:$I$1000,0), MATCH(S$6,Din!$J$3:$AO$3,0)), _xlpm.Status,INDEX('FORÇA DE TRABALHO'!$E$15:$E$999, MATCH($L20,'FORÇA DE TRABALHO'!$C$15:$C$999,0), MATCH(S$6+0,'FORÇA DE TRABALHO'!$E$14:$E$14+0,0)), IF( OR(_xlpm.Prod="",_xlpm.Prod=0), IF(_xlpm.Status="ATIVO",0,_xlpm.Status), _xlpm.Prod ) ), "")} -> 2 | T20: {=IFERROR( _xlfn.LET( _xlpm.Prod,INDEX(Din!$J$4:$AR$1000, MATCH($L20,Din!$I$4:$I$1000,0), MATCH(T$6,Din!$J$3:$AO$3,0)), _xlpm.Status,INDEX('FORÇA DE TRABALHO'!$E$15:$E$999, MATCH($L20,'FORÇA DE TRABALHO'!$C$15:$C$999,0), MATCH(T$6+0,'FORÇA DE TRABALHO'!$E$14:$E$14+0,0)), IF( OR(_xlpm.Prod="",_xlpm.Prod=0), IF(_xlpm.Status="ATIVO",0,_xlpm.Status), _xlpm.Prod ) ), "")} -> 2 | ... AQ20: {=IFERROR( _xlfn.LET( _xlpm.Prod,INDEX(Din!$J$4:$AR$1000, MATCH($L20,Din!$I$4:$I$1000,0), MATCH(AQ$6,Din!$J$3:$AO$3,0)), _xlpm.Status,INDEX('FORÇA DE TRABALHO'!$E$15:$E$999, MATCH($L20,'FORÇA DE TRABALHO'!$C$15:$C$999,0), MATCH(AQ$6+0,'FORÇA DE TRABALHO'!$E$14:$E$14+0,0)), IF( OR(_xlpm.Prod="",_xlpm.Prod=0), IF(_xlpm.Status="ATIVO",0,_xlpm.Status), _xlpm.Prod ) ), "")}
H21: =SUM(M21:AQ21) -> 48 | I21: =ResumoProducao[[#This Row],[Produção]]/ResumoProducao[[#This Row],[Dias Trabalhado]] -> 48 | J21: {=SUMPRODUCT(('FORÇA DE TRABALHO'!$C$15:$C$1007=L21)*('FORÇA DE TRABALHO'!$E$15:$E$1007="ATIVO"))} -> 1 | K21: =IF(I21<2,"4Q",IF(I21<=3,"3Q",IF(I21<=3.9,"2Q","1Q"))) -> 1Q | L21: =IF(Din!A12="","",Din!A12) -> ADÉCIO JÂNIO PEREIRA DE SOUSA | M21: {=IFERROR( _xlfn.LET( _xlpm.Prod,INDEX(Din!$J$4:$AR$1000, MATCH($L21,Din!$I$4:$I$1000,0), MATCH(M$6,Din!$J$3:$AO$3,0)), _xlpm.Status,INDEX('FORÇA DE TRABALHO'!$E$15:$E$999, MATCH($L21,'FORÇA DE TRABALHO'!$C$15:$C$999,0), MATCH(M$6+0,'FORÇA DE TRABALHO'!$E$14:$E$14+0,0)), IF( OR(_xlpm.Prod="",_xlpm.Prod=0), IF(_xlpm.Status="ATIVO",0,_xlpm.Status), _xlpm.Prod ) ), "")} -> 1 | N21: {=IFERROR( _xlfn.LET( _xlpm.Prod,INDEX(Din!$J$4:$AR$1000, MATCH($L21,Din!$I$4:$I$1000,0), MATCH(N$6,Din!$J$3:$AO$3,0)), _xlpm.Status,INDEX('FORÇA DE TRABALHO'!$E$15:$E$999, MATCH($L21,'FORÇA DE TRABALHO'!$C$15:$C$999,0), MATCH(N$6+0,'FORÇA DE TRABALHO'!$E$14:$E$14+0,0)), IF( OR(_xlpm.Prod="",_xlpm.Prod=0), IF(_xlpm.Status="ATIVO",0,_xlpm.Status), _xlpm.Prod ) ), "")} -> 1 | O21: {=IFERROR( _xlfn.LET( _xlpm.Prod,INDEX(Din!$J$4:$AR$1000, MATCH($L21,Din!$I$4:$I$1000,0), MATCH(O$6,Din!$J$3:$AO$3,0)), _xlpm.Status,INDEX('FORÇA DE TRABALHO'!$E$15:$E$999, MATCH($L21,'FORÇA DE TRABALHO'!$C$15:$C$999,0), MATCH(O$6+0,'FORÇA DE TRABALHO'!$E$14:$E$14+0,0)), IF( OR(_xlpm.Prod="",_xlpm.Prod=0), IF(_xlpm.Status="ATIVO",0,_xlpm.Status), _xlpm.Prod ) ), "")} -> 2 | P21: {=IFERROR( _xlfn.LET( _xlpm.Prod,INDEX(Din!$J$4:$AR$1000, MATCH($L21,Din!$I$4:$I$1000,0), MATCH(P$6,Din!$J$3:$AO$3,0)), _xlpm.Status,INDEX('FORÇA DE TRABALHO'!$E$15:$E$999, MATCH($L21,'FORÇA DE TRABALHO'!$C$15:$C$999,0), MATCH(P$6+0,'FORÇA DE TRABALHO'!$E$14:$E$14+0,0)), IF( OR(_xlpm.Prod="",_xlpm.Prod=0), IF(_xlpm.Status="ATIVO",0,_xlpm.Status), _xlpm.Prod ) ), "")} -> 2 | Q21: {=IFERROR( _xlfn.LET( _xlpm.Prod,INDEX(Din!$J$4:$AR$1000, MATCH($L21,Din!$I$4:$I$1000,0), MATCH(Q$6,Din!$J$3:$AO$3,0)), _xlpm.Status,INDEX('FORÇA DE TRABALHO'!$E$15:$E$999, MATCH($L21,'FORÇA DE TRABALHO'!$C$15:$C$999,0), MATCH(Q$6+0,'FORÇA DE TRABALHO'!$E$14:$E$14+0,0)), IF( OR(_xlpm.Prod="",_xlpm.Prod=0), IF(_xlpm.Status="ATIVO",0,_xlpm.Status), _xlpm.Prod ) ), "")} | R21: {=IFERROR( _xlfn.LET( _xlpm.Prod,INDEX(Din!$J$4:$AR$1000, MATCH($L21,Din!$I$4:$I$1000,0), MATCH(R$6,Din!$J$3:$AO$3,0)), _xlpm.Status,INDEX('FORÇA DE TRABALHO'!$E$15:$E$999, MATCH($L21,'FORÇA DE TRABALHO'!$C$15:$C$999,0), MATCH(R$6+0,'FORÇA DE TRABALHO'!$E$14:$E$14+0,0)), IF( OR(_xlpm.Prod="",_xlpm.Prod=0), IF(_xlpm.Status="ATIVO",0,_xlpm.Status), _xlpm.Prod ) ), "")} -> 2 | S21: {=IFERROR( _xlfn.LET( _xlpm.Prod,INDEX(Din!$J$4:$AR$1000, MATCH($L21,Din!$I$4:$I$1000,0), MATCH(S$6,Din!$J$3:$AO$3,0)), _xlpm.Status,INDEX('FORÇA DE TRABALHO'!$E$15:$E$999, MATCH($L21,'FORÇA DE TRABALHO'!$C$15:$C$999,0), MATCH(S$6+0,'FORÇA DE TRABALHO'!$E$14:$E$14+0,0)), IF( OR(_xlpm.Prod="",_xlpm.Prod=0), IF(_xlpm.Status="ATIVO",0,_xlpm.Status), _xlpm.Prod ) ), "")} -> 4 | T21: {=IFERROR( _xlfn.LET( _xlpm.Prod,INDEX(Din!$J$4:$AR$1000, MATCH($L21,Din!$I$4:$I$1000,0), MATCH(T$6,Din!$J$3:$AO$3,0)), _xlpm.Status,INDEX('FORÇA DE TRABALHO'!$E$15:$E$999, MATCH($L21,'FORÇA DE TRABALHO'!$C$15:$C$999,0), MATCH(T$6+0,'FORÇA DE TRABALHO'!$E$14:$E$14+0,0)), IF( OR(_xlpm.Prod="",_xlpm.Prod=0), IF(_xlpm.Status="ATIVO",0,_xlpm.Status), _xlpm.Prod ) ), "")} -> 2 | ... AQ21: {=IFERROR( _xlfn.LET( _xlpm.Prod,INDEX(Din!$J$4:$AR$1000, MATCH($L21,Din!$I$4:$I$1000,0), MATCH(AQ$6,Din!$J$3:$AO$3,0)), _xlpm.Status,INDEX('FORÇA DE TRABALHO'!$E$15:$E$999, MATCH($L21,'FORÇA DE TRABALHO'!$C$15:$C$999,0), MATCH(AQ$6+0,'FORÇA DE TRABALHO'!$E$14:$E$14+0,0)), IF( OR(_xlpm.Prod="",_xlpm.Prod=0), IF(_xlpm.Status="ATIVO",0,_xlpm.Status), _xlpm.Prod ) ), "")}
H22: =SUM(M22:AQ22) -> 51 | I22: =ResumoProducao[[#This Row],[Produção]]/ResumoProducao[[#This Row],[Dias Trabalhado]] -> 51 | J22: {=SUMPRODUCT(('FORÇA DE TRABALHO'!$C$15:$C$1007=L22)*('FORÇA DE TRABALHO'!$E$15:$E$1007="ATIVO"))} -> 1 | K22: =IF(I22<2,"4Q",IF(I22<=3,"3Q",IF(I22<=3.9,"2Q","1Q"))) -> 1Q | L22: =IF(Din!A13="","",Din!A13) -> EDMILSON HONORATO DE SANTANA JUNIOR | M22: {=IFERROR( _xlfn.LET( _xlpm.Prod,INDEX(Din!$J$4:$AR$1000, MATCH($L22,Din!$I$4:$I$1000,0), MATCH(M$6,Din!$J$3:$AO$3,0)), _xlpm.Status,INDEX('FORÇA DE TRABALHO'!$E$15:$E$999, MATCH($L22,'FORÇA DE TRABALHO'!$C$15:$C$999,0), MATCH(M$6+0,'FORÇA DE TRABALHO'!$E$14:$E$14+0,0)), IF( OR(_xlpm.Prod="",_xlpm.Prod=0), IF(_xlpm.Status="ATIVO",0,_xlpm.Status), _xlpm.Prod ) ), "")} -> 2 | N22: {=IFERROR( _xlfn.LET( _xlpm.Prod,INDEX(Din!$J$4:$AR$1000, MATCH($L22,Din!$I$4:$I$1000,0), MATCH(N$6,Din!$J$3:$AO$3,0)), _xlpm.Status,INDEX('FORÇA DE TRABALHO'!$E$15:$E$999, MATCH($L22,'FORÇA DE TRABALHO'!$C$15:$C$999,0), MATCH(N$6+0,'FORÇA DE TRABALHO'!$E$14:$E$14+0,0)), IF( OR(_xlpm.Prod="",_xlpm.Prod=0), IF(_xlpm.Status="ATIVO",0,_xlpm.Status), _xlpm.Prod ) ), "")} -> 3 | O22: {=IFERROR( _xlfn.LET( _xlpm.Prod,INDEX(Din!$J$4:$AR$1000, MATCH($L22,Din!$I$4:$I$1000,0), MATCH(O$6,Din!$J$3:$AO$3,0)), _xlpm.Status,INDEX('FORÇA DE TRABALHO'!$E$15:$E$999, MATCH($L22,'FORÇA DE TRABALHO'!$C$15:$C$999,0), MATCH(O$6+0,'FORÇA DE TRABALHO'!$E$14:$E$14+0,0)), IF( OR(_xlpm.Prod="",_xlpm.Prod=0), IF(_xlpm.Status="ATIVO",0,_xlpm.Status), _xlpm.Prod ) ), "")} -> 2 | P22: {=IFERROR( _xlfn.LET( _xlpm.Prod,INDEX(Din!$J$4:$AR$1000, MATCH($L22,Din!$I$4:$I$1000,0), MATCH(P$6,Din!$J$3:$AO$3,0)), _xlpm.Status,INDEX('FORÇA DE TRABALHO'!$E$15:$E$999, MATCH($L22,'FORÇA DE TRABALHO'!$C$15:$C$999,0), MATCH(P$6+0,'FORÇA DE TRABALHO'!$E$14:$E$14+0,0)), IF( OR(_xlpm.Prod="",_xlpm.Prod=0), IF(_xlpm.Status="ATIVO",0,_xlpm.Status), _xlpm.Prod ) ), "")} -> 2 | Q22: {=IFERROR( _xlfn.LET( _xlpm.Prod,INDEX(Din!$J$4:$AR$1000, MATCH($L22,Din!$I$4:$I$1000,0), MATCH(Q$6,Din!$J$3:$AO$3,0)), _xlpm.Status,INDEX('FORÇA DE TRABALHO'!$E$15:$E$999, MATCH($L22,'FORÇA DE TRABALHO'!$C$15:$C$999,0), MATCH(Q$6+0,'FORÇA DE TRABALHO'!$E$14:$E$14+0,0)), IF( OR(_xlpm.Prod="",_xlpm.Prod=0), IF(_xlpm.Status="ATIVO",0,_xlpm.Status), _xlpm.Prod ) ), "")} | R22: {=IFERROR( _xlfn.LET( _xlpm.Prod,INDEX(Din!$J$4:$AR$1000, MATCH($L22,Din!$I$4:$I$1000,0), MATCH(R$6,Din!$J$3:$AO$3,0)), _xlpm.Status,INDEX('FORÇA DE TRABALHO'!$E$15:$E$999, MATCH($L22,'FORÇA DE TRABALHO'!$C$15:$C$999,0), MATCH(R$6+0,'FORÇA DE TRABALHO'!$E$14:$E$14+0,0)), IF( OR(_xlpm.Prod="",_xlpm.Prod=0), IF(_xlpm.Status="ATIVO",0,_xlpm.Status), _xlpm.Prod ) ), "")} | S22: {=IFERROR( _xlfn.LET( _xlpm.Prod,INDEX(Din!$J$4:$AR$1000, MATCH($L22,Din!$I$4:$I$1000,0), MATCH(S$6,Din!$J$3:$AO$3,0)), _xlpm.Status,INDEX('FORÇA DE TRABALHO'!$E$15:$E$999, MATCH($L22,'FORÇA DE TRABALHO'!$C$15:$C$999,0), MATCH(S$6+0,'FORÇA DE TRABALHO'!$E$14:$E$14+0,0)), IF( OR(_xlpm.Prod="",_xlpm.Prod=0), IF(_xlpm.Status="ATIVO",0,_xlpm.Status), _xlpm.Prod ) ), "")} -> 2 | T22: {=IFERROR( _xlfn.LET( _xlpm.Prod,INDEX(Din!$J$4:$AR$1000, MATCH($L22,Din!$I$4:$I$1000,0), MATCH(T$6,Din!$J$3:$AO$3,0)), _xlpm.Status,INDEX('FORÇA DE TRABALHO'!$E$15:$E$999, MATCH($L22,'FORÇA DE TRABALHO'!$C$15:$C$999,0), MATCH(T$6+0,'FORÇA DE TRABALHO'!$E$14:$E$14+0,0)), IF( OR(_xlpm.Prod="",_xlpm.Prod=0), IF(_xlpm.Status="ATIVO",0,_xlpm.Status), _xlpm.Prod ) ), "")} -> 3 | ... AQ22: {=IFERROR( _xlfn.LET( _xlpm.Prod,INDEX(Din!$J$4:$AR$1000, MATCH($L22,Din!$I$4:$I$1000,0), MATCH(AQ$6,Din!$J$3:$AO$3,0)), _xlpm.Status,INDEX('FORÇA DE TRABALHO'!$E$15:$E$999, MATCH($L22,'FORÇA DE TRABALHO'!$C$15:$C$999,0), MATCH(AQ$6+0,'FORÇA DE TRABALHO'!$E$14:$E$14+0,0)), IF( OR(_xlpm.Prod="",_xlpm.Prod=0), IF(_xlpm.Status="ATIVO",0,_xlpm.Status), _xlpm.Prod ) ), "")}
H23: =SUM(M23:AQ23) -> 48 | I23: =ResumoProducao[[#This Row],[Produção]]/ResumoProducao[[#This Row],[Dias Trabalhado]] -> 48 | J23: {=SUMPRODUCT(('FORÇA DE TRABALHO'!$C$15:$C$1007=L23)*('FORÇA DE TRABALHO'!$E$15:$E$1007="ATIVO"))} -> 1 | K23: =IF(I23<2,"4Q",IF(I23<=3,"3Q",IF(I23<=3.9,"2Q","1Q"))) -> 1Q | L23: =IF(Din!A14="","",Din!A14) -> CARLOS EDUARDO DA SILVA QUEIROZ | M23: {=IFERROR( _xlfn.LET( _xlpm.Prod,INDEX(Din!$J$4:$AR$1000, MATCH($L23,Din!$I$4:$I$1000,0), MATCH(M$6,Din!$J$3:$AO$3,0)), _xlpm.Status,INDEX('FORÇA DE TRABALHO'!$E$15:$E$999, MATCH($L23,'FORÇA DE TRABALHO'!$C$15:$C$999,0), MATCH(M$6+0,'FORÇA DE TRABALHO'!$E$14:$E$14+0,0)), IF( OR(_xlpm.Prod="",_xlpm.Prod=0), IF(_xlpm.Status="ATIVO",0,_xlpm.Status), _xlpm.Prod ) ), "")} -> 3 | N23: {=IFERROR( _xlfn.LET( _xlpm.Prod,INDEX(Din!$J$4:$AR$1000, MATCH($L23,Din!$I$4:$I$1000,0), MATCH(N$6,Din!$J$3:$AO$3,0)), _xlpm.Status,INDEX('FORÇA DE TRABALHO'!$E$15:$E$999, MATCH($L23,'FORÇA DE TRABALHO'!$C$15:$C$999,0), MATCH(N$6+0,'FORÇA DE TRABALHO'!$E$14:$E$14+0,0)), IF( OR(_xlpm.Prod="",_xlpm.Prod=0), IF(_xlpm.Status="ATIVO",0,_xlpm.Status), _xlpm.Prod ) ), "")} -> 3 | O23: {=IFERROR( _xlfn.LET( _xlpm.Prod,INDEX(Din!$J$4:$AR$1000, MATCH($L23,Din!$I$4:$I$1000,0), MATCH(O$6,Din!$J$3:$AO$3,0)), _xlpm.Status,INDEX('FORÇA DE TRABALHO'!$E$15:$E$999, MATCH($L23,'FORÇA DE TRABALHO'!$C$15:$C$999,0), MATCH(O$6+0,'FORÇA DE TRABALHO'!$E$14:$E$14+0,0)), IF( OR(_xlpm.Prod="",_xlpm.Prod=0), IF(_xlpm.Status="ATIVO",0,_xlpm.Status), _xlpm.Prod ) ), "")} -> 1 | P23: {=IFERROR( _xlfn.LET( _xlpm.Prod,INDEX(Din!$J$4:$AR$1000, MATCH($L23,Din!$I$4:$I$1000,0), MATCH(P$6,Din!$J$3:$AO$3,0)), _xlpm.Status,INDEX('FORÇA DE TRABALHO'!$E$15:$E$999, MATCH($L23,'FORÇA DE TRABALHO'!$C$15:$C$999,0), MATCH(P$6+0,'FORÇA DE TRABALHO'!$E$14:$E$14+0,0)), IF( OR(_xlpm.Prod="",_xlpm.Prod=0), IF(_xlpm.Status="ATIVO",0,_xlpm.Status), _xlpm.Prod ) ), "")} -> 2 | Q23: {=IFERROR( _xlfn.LET( _xlpm.Prod,INDEX(Din!$J$4:$AR$1000, MATCH($L23,Din!$I$4:$I$1000,0), MATCH(Q$6,Din!$J$3:$AO$3,0)), _xlpm.Status,INDEX('FORÇA DE TRABALHO'!$E$15:$E$999, MATCH($L23,'FORÇA DE TRABALHO'!$C$15:$C$999,0), MATCH(Q$6+0,'FORÇA DE TRABALHO'!$E$14:$E$14+0,0)), IF( OR(_xlpm.Prod="",_xlpm.Prod=0), IF(_xlpm.Status="ATIVO",0,_xlpm.Status), _xlpm.Prod ) ), "")} | R23: {=IFERROR( _xlfn.LET( _xlpm.Prod,INDEX(Din!$J$4:$AR$1000, MATCH($L23,Din!$I$4:$I$1000,0), MATCH(R$6,Din!$J$3:$AO$3,0)), _xlpm.Status,INDEX('FORÇA DE TRABALHO'!$E$15:$E$999, MATCH($L23,'FORÇA DE TRABALHO'!$C$15:$C$999,0), MATCH(R$6+0,'FORÇA DE TRABALHO'!$E$14:$E$14+0,0)), IF( OR(_xlpm.Prod="",_xlpm.Prod=0), IF(_xlpm.Status="ATIVO",0,_xlpm.Status), _xlpm.Prod ) ), "")} -> 2 | S23: {=IFERROR( _xlfn.LET( _xlpm.Prod,INDEX(Din!$J$4:$AR$1000, MATCH($L23,Din!$I$4:$I$1000,0), MATCH(S$6,Din!$J$3:$AO$3,0)), _xlpm.Status,INDEX('FORÇA DE TRABALHO'!$E$15:$E$999, MATCH($L23,'FORÇA DE TRABALHO'!$C$15:$C$999,0), MATCH(S$6+0,'FORÇA DE TRABALHO'!$E$14:$E$14+0,0)), IF( OR(_xlpm.Prod="",_xlpm.Prod=0), IF(_xlpm.Status="ATIVO",0,_xlpm.Status), _xlpm.Prod ) ), "")} -> 4 | T23: {=IFERROR( _xlfn.LET( _xlpm.Prod,INDEX(Din!$J$4:$AR$1000, MATCH($L23,Din!$I$4:$I$1000,0), MATCH(T$6,Din!$J$3:$AO$3,0)), _xlpm.Status,INDEX('FORÇA DE TRABALHO'!$E$15:$E$999, MATCH($L23,'FORÇA DE TRABALHO'!$C$15:$C$999,0), MATCH(T$6+0,'FORÇA DE TRABALHO'!$E$14:$E$14+0,0)), IF( OR(_xlpm.Prod="",_xlpm.Prod=0), IF(_xlpm.Status="ATIVO",0,_xlpm.Status), _xlpm.Prod ) ), "")} -> 3 | ... AQ23: {=IFERROR( _xlfn.LET( _xlpm.Prod,INDEX(Din!$J$4:$AR$1000, MATCH($L23,Din!$I$4:$I$1000,0), MATCH(AQ$6,Din!$J$3:$AO$3,0)), _xlpm.Status,INDEX('FORÇA DE TRABALHO'!$E$15:$E$999, MATCH($L23,'FORÇA DE TRABALHO'!$C$15:$C$999,0), MATCH(AQ$6+0,'FORÇA DE TRABALHO'!$E$14:$E$14+0,0)), IF( OR(_xlpm.Prod="",_xlpm.Prod=0), IF(_xlpm.Status="ATIVO",0,_xlpm.Status), _xlpm.Prod ) ), "")}
H24: =SUM(M24:AQ24) -> 43 | I24: =ResumoProducao[[#This Row],[Produção]]/ResumoProducao[[#This Row],[Dias Trabalhado]] -> 43 | J24: {=SUMPRODUCT(('FORÇA DE TRABALHO'!$C$15:$C$1007=L24)*('FORÇA DE TRABALHO'!$E$15:$E$1007="ATIVO"))} -> 1 | K24: =IF(I24<2,"4Q",IF(I24<=3,"3Q",IF(I24<=3.9,"2Q","1Q"))) -> 1Q | L24: =IF(Din!A15="","",Din!A15) -> FRANCISCO EDVALDO CARDOSO CARNEIRO | M24: {=IFERROR( _xlfn.LET( _xlpm.Prod,INDEX(Din!$J$4:$AR$1000, MATCH($L24,Din!$I$4:$I$1000,0), MATCH(M$6,Din!$J$3:$AO$3,0)), _xlpm.Status,INDEX('FORÇA DE TRABALHO'!$E$15:$E$999, MATCH($L24,'FORÇA DE TRABALHO'!$C$15:$C$999,0), MATCH(M$6+0,'FORÇA DE TRABALHO'!$E$14:$E$14+0,0)), IF( OR(_xlpm.Prod="",_xlpm.Prod=0), IF(_xlpm.Status="ATIVO",0,_xlpm.Status), _xlpm.Prod ) ), "")} -> 2 | N24: {=IFERROR( _xlfn.LET( _xlpm.Prod,INDEX(Din!$J$4:$AR$1000, MATCH($L24,Din!$I$4:$I$1000,0), MATCH(N$6,Din!$J$3:$AO$3,0)), _xlpm.Status,INDEX('FORÇA DE TRABALHO'!$E$15:$E$999, MATCH($L24,'FORÇA DE TRABALHO'!$C$15:$C$999,0), MATCH(N$6+0,'FORÇA DE TRABALHO'!$E$14:$E$14+0,0)), IF( OR(_xlpm.Prod="",_xlpm.Prod=0), IF(_xlpm.Status="ATIVO",0,_xlpm.Status), _xlpm.Prod ) ), "")} -> 2 | O24: {=IFERROR( _xlfn.LET( _xlpm.Prod,INDEX(Din!$J$4:$AR$1000, MATCH($L24,Din!$I$4:$I$1000,0), MATCH(O$6,Din!$J$3:$AO$3,0)), _xlpm.Status,INDEX('FORÇA DE TRABALHO'!$E$15:$E$999, MATCH($L24,'FORÇA DE TRABALHO'!$C$15:$C$999,0), MATCH(O$6+0,'FORÇA DE TRABALHO'!$E$14:$E$14+0,0)), IF( OR(_xlpm.Prod="",_xlpm.Prod=0), IF(_xlpm.Status="ATIVO",0,_xlpm.Status), _xlpm.Prod ) ), "")} -> 1 | P24: {=IFERROR( _xlfn.LET( _xlpm.Prod,INDEX(Din!$J$4:$AR$1000, MATCH($L24,Din!$I$4:$I$1000,0), MATCH(P$6,Din!$J$3:$AO$3,0)), _xlpm.Status,INDEX('FORÇA DE TRABALHO'!$E$15:$E$999, MATCH($L24,'FORÇA DE TRABALHO'!$C$15:$C$999,0), MATCH(P$6+0,'FORÇA DE TRABALHO'!$E$14:$E$14+0,0)), IF( OR(_xlpm.Prod="",_xlpm.Prod=0), IF(_xlpm.Status="ATIVO",0,_xlpm.Status), _xlpm.Prod ) ), "")} -> 2 | Q24: {=IFERROR( _xlfn.LET( _xlpm.Prod,INDEX(Din!$J$4:$AR$1000, MATCH($L24,Din!$I$4:$I$1000,0), MATCH(Q$6,Din!$J$3:$AO$3,0)), _xlpm.Status,INDEX('FORÇA DE TRABALHO'!$E$15:$E$999, MATCH($L24,'FORÇA DE TRABALHO'!$C$15:$C$999,0), MATCH(Q$6+0,'FORÇA DE TRABALHO'!$E$14:$E$14+0,0)), IF( OR(_xlpm.Prod="",_xlpm.Prod=0), IF(_xlpm.Status="ATIVO",0,_xlpm.Status), _xlpm.Prod ) ), "")} | R24: {=IFERROR( _xlfn.LET( _xlpm.Prod,INDEX(Din!$J$4:$AR$1000, MATCH($L24,Din!$I$4:$I$1000,0), MATCH(R$6,Din!$J$3:$AO$3,0)), _xlpm.Status,INDEX('FORÇA DE TRABALHO'!$E$15:$E$999, MATCH($L24,'FORÇA DE TRABALHO'!$C$15:$C$999,0), MATCH(R$6+0,'FORÇA DE TRABALHO'!$E$14:$E$14+0,0)), IF( OR(_xlpm.Prod="",_xlpm.Prod=0), IF(_xlpm.Status="ATIVO",0,_xlpm.Status), _xlpm.Prod ) ), "")} | S24: {=IFERROR( _xlfn.LET( _xlpm.Prod,INDEX(Din!$J$4:$AR$1000, MATCH($L24,Din!$I$4:$I$1000,0), MATCH(S$6,Din!$J$3:$AO$3,0)), _xlpm.Status,INDEX('FORÇA DE TRABALHO'!$E$15:$E$999, MATCH($L24,'FORÇA DE TRABALHO'!$C$15:$C$999,0), MATCH(S$6+0,'FORÇA DE TRABALHO'!$E$14:$E$14+0,0)), IF( OR(_xlpm.Prod="",_xlpm.Prod=0), IF(_xlpm.Status="ATIVO",0,_xlpm.Status), _xlpm.Prod ) ), "")} -> 2 | T24: {=IFERROR( _xlfn.LET( _xlpm.Prod,INDEX(Din!$J$4:$AR$1000, MATCH($L24,Din!$I$4:$I$1000,0), MATCH(T$6,Din!$J$3:$AO$3,0)), _xlpm.Status,INDEX('FORÇA DE TRABALHO'!$E$15:$E$999, MATCH($L24,'FORÇA DE TRABALHO'!$C$15:$C$999,0), MATCH(T$6+0,'FORÇA DE TRABALHO'!$E$14:$E$14+0,0)), IF( OR(_xlpm.Prod="",_xlpm.Prod=0), IF(_xlpm.Status="ATIVO",0,_xlpm.Status), _xlpm.Prod ) ), "")} -> 1 | ... AQ24: {=IFERROR( _xlfn.LET( _xlpm.Prod,INDEX(Din!$J$4:$AR$1000, MATCH($L24,Din!$I$4:$I$1000,0), MATCH(AQ$6,Din!$J$3:$AO$3,0)), _xlpm.Status,INDEX('FORÇA DE TRABALHO'!$E$15:$E$999, MATCH($L24,'FORÇA DE TRABALHO'!$C$15:$C$999,0), MATCH(AQ$6+0,'FORÇA DE TRABALHO'!$E$14:$E$14+0,0)), IF( OR(_xlpm.Prod="",_xlpm.Prod=0), IF(_xlpm.Status="ATIVO",0,_xlpm.Status), _xlpm.Prod ) ), "")}
... H61: =SUM(M61:AQ61) -> 18 | I61: =ResumoProducao[[#This Row],[Produção]]/ResumoProducao[[#This Row],[Dias Trabalhado]] -> 18 | J61: {=SUMPRODUCT(('FORÇA DE TRABALHO'!$C$15:$C$1007=L61)*('FORÇA DE TRABALHO'!$E$15:$E$1007="ATIVO"))} -> 1 | K61: =IF(I61<2,"4Q",IF(I61<=3,"3Q",IF(I61<=3.9,"2Q","1Q"))) -> 1Q | L61: =IF(Din!A52="","",Din!A52) -> LAISE BRITO BOTELHO | M61: {=IFERROR( _xlfn.LET( _xlpm.Prod,INDEX(Din!$J$4:$AR$1000, MATCH($L61,Din!$I$4:$I$1000,0), MATCH(M$6,Din!$J$3:$AO$3,0)), _xlpm.Status,INDEX('FORÇA DE TRABALHO'!$E$15:$E$999, MATCH($L61,'FORÇA DE TRABALHO'!$C$15:$C$999,0), MATCH(M$6+0,'FORÇA DE TRABALHO'!$E$14:$E$14+0,0)), IF( OR(_xlpm.Prod="",_xlpm.Prod=0), IF(_xlpm.Status="ATIVO",0,_xlpm.Status), _xlpm.Prod ) ), "")} -> 1 | N61: {=IFERROR( _xlfn.LET( _xlpm.Prod,INDEX(Din!$J$4:$AR$1000, MATCH($L61,Din!$I$4:$I$1000,0), MATCH(N$6,Din!$J$3:$AO$3,0)), _xlpm.Status,INDEX('FORÇA DE TRABALHO'!$E$15:$E$999, MATCH($L61,'FORÇA DE TRABALHO'!$C$15:$C$999,0), MATCH(N$6+0,'FORÇA DE TRABALHO'!$E$14:$E$14+0,0)), IF( OR(_xlpm.Prod="",_xlpm.Prod=0), IF(_xlpm.Status="ATIVO",0,_xlpm.Status), _xlpm.Prod ) ), "")} | O61: {=IFERROR( _xlfn.LET( _xlpm.Prod,INDEX(Din!$J$4:$AR$1000, MATCH($L61,Din!$I$4:$I$1000,0), MATCH(O$6,Din!$J$3:$AO$3,0)), _xlpm.Status,INDEX('FORÇA DE TRABALHO'!$E$15:$E$999, MATCH($L61,'FORÇA DE TRABALHO'!$C$15:$C$999,0), MATCH(O$6+0,'FORÇA DE TRABALHO'!$E$14:$E$14+0,0)), IF( OR(_xlpm.Prod="",_xlpm.Prod=0), IF(_xlpm.Status="ATIVO",0,_xlpm.Status), _xlpm.Prod ) ), "")} -> 2 | P61: {=IFERROR( _xlfn.LET( _xlpm.Prod,INDEX(Din!$J$4:$AR$1000, MATCH($L61,Din!$I$4:$I$1000,0), MATCH(P$6,Din!$J$3:$AO$3,0)), _xlpm.Status,INDEX('FORÇA DE TRABALHO'!$E$15:$E$999, MATCH($L61,'FORÇA DE TRABALHO'!$C$15:$C$999,0), MATCH(P$6+0,'FORÇA DE TRABALHO'!$E$14:$E$14+0,0)), IF( OR(_xlpm.Prod="",_xlpm.Prod=0), IF(_xlpm.Status="ATIVO",0,_xlpm.Status), _xlpm.Prod ) ), "")} -> 2 | Q61: {=IFERROR( _xlfn.LET( _xlpm.Prod,INDEX(Din!$J$4:$AR$1000, MATCH($L61,Din!$I$4:$I$1000,0), MATCH(Q$6,Din!$J$3:$AO$3,0)), _xlpm.Status,INDEX('FORÇA DE TRABALHO'!$E$15:$E$999, MATCH($L61,'FORÇA DE TRABALHO'!$C$15:$C$999,0), MATCH(Q$6+0,'FORÇA DE TRABALHO'!$E$14:$E$14+0,0)), IF( OR(_xlpm.Prod="",_xlpm.Prod=0), IF(_xlpm.Status="ATIVO",0,_xlpm.Status), _xlpm.Prod ) ), "")} | R61: {=IFERROR( _xlfn.LET( _xlpm.Prod,INDEX(Din!$J$4:$AR$1000, MATCH($L61,Din!$I$4:$I$1000,0), MATCH(R$6,Din!$J$3:$AO$3,0)), _xlpm.Status,INDEX('FORÇA DE TRABALHO'!$E$15:$E$999, MATCH($L61,'FORÇA DE TRABALHO'!$C$15:$C$999,0), MATCH(R$6+0,'FORÇA DE TRABALHO'!$E$14:$E$14+0,0)), IF( OR(_xlpm.Prod="",_xlpm.Prod=0), IF(_xlpm.Status="ATIVO",0,_xlpm.Status), _xlpm.Prod ) ), "")} -> 1 | S61: {=IFERROR( _xlfn.LET( _xlpm.Prod,INDEX(Din!$J$4:$AR$1000, MATCH($L61,Din!$I$4:$I$1000,0), MATCH(S$6,Din!$J$3:$AO$3,0)), _xlpm.Status,INDEX('FORÇA DE TRABALHO'!$E$15:$E$999, MATCH($L61,'FORÇA DE TRABALHO'!$C$15:$C$999,0), MATCH(S$6+0,'FORÇA DE TRABALHO'!$E$14:$E$14+0,0)), IF( OR(_xlpm.Prod="",_xlpm.Prod=0), IF(_xlpm.Status="ATIVO",0,_xlpm.Status), _xlpm.Prod ) ), "")} -> 2 | T61: {=IFERROR( _xlfn.LET( _xlpm.Prod,INDEX(Din!$J$4:$AR$1000, MATCH($L61,Din!$I$4:$I$1000,0), MATCH(T$6,Din!$J$3:$AO$3,0)), _xlpm.Status,INDEX('FORÇA DE TRABALHO'!$E$15:$E$999, MATCH($L61,'FORÇA DE TRABALHO'!$C$15:$C$999,0), MATCH(T$6+0,'FORÇA DE TRABALHO'!$E$14:$E$14+0,0)), IF( OR(_xlpm.Prod="",_xlpm.Prod=0), IF(_xlpm.Status="ATIVO",0,_xlpm.Status), _xlpm.Prod ) ), "")} | ... AQ61: {=IFERROR( _xlfn.LET( _xlpm.Prod,INDEX(Din!$J$4:$AR$1000, MATCH($L61,Din!$I$4:$I$1000,0), MATCH(AQ$6,Din!$J$3:$AO$3,0)), _xlpm.Status,INDEX('FORÇA DE TRABALHO'!$E$15:$E$999, MATCH($L61,'FORÇA DE TRABALHO'!$C$15:$C$999,0), MATCH(AQ$6+0,'FORÇA DE TRABALHO'!$E$14:$E$14+0,0)), IF( OR(_xlpm.Prod="",_xlpm.Prod=0), IF(_xlpm.Status="ATIVO",0,_xlpm.Status), _xlpm.Prod ) ), "")}
H62: =SUM(M62:AQ62) -> 14 | I62: =ResumoProducao[[#Totals],[Produção]]/ResumoProducao[[#Totals],[Dias Trabalhado]] -> 14 | J62: {=SUMPRODUCT(('FORÇA DE TRABALHO'!$C$15:$C$1007=L62)*('FORÇA DE TRABALHO'!$E$15:$E$1007="ATIVO"))} -> 1 | K62: =IF(I62<2,"4Q",IF(I62<=3,"3Q",IF(I62<=3.9,"2Q","1Q"))) -> 1Q | L62: =IF(Din!A53="","",Din!A53) -> THIAGO PEREIRA LIMA | M62: {=IFERROR( _xlfn.LET( _xlpm.Prod,INDEX(Din!$J$4:$AR$1000, MATCH($L62,Din!$I$4:$I$1000,0), MATCH(M$6,Din!$J$3:$AO$3,0)), _xlpm.Status,INDEX('FORÇA DE TRABALHO'!$E$15:$E$999, MATCH($L62,'FORÇA DE TRABALHO'!$C$15:$C$999,0), MATCH(M$6+0,'FORÇA DE TRABALHO'!$E$14:$E$14+0,0)), IF( OR(_xlpm.Prod="",_xlpm.Prod=0), IF(_xlpm.Status="ATIVO",0,_xlpm.Status), _xlpm.Prod ) ), "")} | N62: {=IFERROR( _xlfn.LET( _xlpm.Prod,INDEX(Din!$J$4:$AR$1000, MATCH($L62,Din!$I$4:$I$1000,0), MATCH(N$6,Din!$J$3:$AO$3,0)), _xlpm.Status,INDEX('FORÇA DE TRABALHO'!$E$15:$E$999, MATCH($L62,'FORÇA DE TRABALHO'!$C$15:$C$999,0), MATCH(N$6+0,'FORÇA DE TRABALHO'!$E$14:$E$14+0,0)), IF( OR(_xlpm.Prod="",_xlpm.Prod=0), IF(_xlpm.Status="ATIVO",0,_xlpm.Status), _xlpm.Prod ) ), "")} -> 1 | O62: {=IFERROR( _xlfn.LET( _xlpm.Prod,INDEX(Din!$J$4:$AR$1000, MATCH($L62,Din!$I$4:$I$1000,0), MATCH(O$6,Din!$J$3:$AO$3,0)), _xlpm.Status,INDEX('FORÇA DE TRABALHO'!$E$15:$E$999, MATCH($L62,'FORÇA DE TRABALHO'!$C$15:$C$999,0), MATCH(O$6+0,'FORÇA DE TRABALHO'!$E$14:$E$14+0,0)), IF( OR(_xlpm.Prod="",_xlpm.Prod=0), IF(_xlpm.Status="ATIVO",0,_xlpm.Status), _xlpm.Prod ) ), "")} -> 1 | P62: {=IFERROR( _xlfn.LET( _xlpm.Prod,INDEX(Din!$J$4:$AR$1000, MATCH($L62,Din!$I$4:$I$1000,0), MATCH(P$6,Din!$J$3:$AO$3,0)), _xlpm.Status,INDEX('FORÇA DE TRABALHO'!$E$15:$E$999, MATCH($L62,'FORÇA DE TRABALHO'!$C$15:$C$999,0), MATCH(P$6+0,'FORÇA DE TRABALHO'!$E$14:$E$14+0,0)), IF( OR(_xlpm.Prod="",_xlpm.Prod=0), IF(_xlpm.Status="ATIVO",0,_xlpm.Status), _xlpm.Prod ) ), "")} -> 1 | Q62: {=IFERROR( _xlfn.LET( _xlpm.Prod,INDEX(Din!$J$4:$AR$1000, MATCH($L62,Din!$I$4:$I$1000,0), MATCH(Q$6,Din!$J$3:$AO$3,0)), _xlpm.Status,INDEX('FORÇA DE TRABALHO'!$E$15:$E$999, MATCH($L62,'FORÇA DE TRABALHO'!$C$15:$C$999,0), MATCH(Q$6+0,'FORÇA DE TRABALHO'!$E$14:$E$14+0,0)), IF( OR(_xlpm.Prod="",_xlpm.Prod=0), IF(_xlpm.Status="ATIVO",0,_xlpm.Status), _xlpm.Prod ) ), "")} | R62: {=IFERROR( _xlfn.LET( _xlpm.Prod,INDEX(Din!$J$4:$AR$1000, MATCH($L62,Din!$I$4:$I$1000,0), MATCH(R$6,Din!$J$3:$AO$3,0)), _xlpm.Status,INDEX('FORÇA DE TRABALHO'!$E$15:$E$999, MATCH($L62,'FORÇA DE TRABALHO'!$C$15:$C$999,0), MATCH(R$6+0,'FORÇA DE TRABALHO'!$E$14:$E$14+0,0)), IF( OR(_xlpm.Prod="",_xlpm.Prod=0), IF(_xlpm.Status="ATIVO",0,_xlpm.Status), _xlpm.Prod ) ), "")} -> 1 | S62: {=IFERROR( _xlfn.LET( _xlpm.Prod,INDEX(Din!$J$4:$AR$1000, MATCH($L62,Din!$I$4:$I$1000,0), MATCH(S$6,Din!$J$3:$AO$3,0)), _xlpm.Status,INDEX('FORÇA DE TRABALHO'!$E$15:$E$999, MATCH($L62,'FORÇA DE TRABALHO'!$C$15:$C$999,0), MATCH(S$6+0,'FORÇA DE TRABALHO'!$E$14:$E$14+0,0)), IF( OR(_xlpm.Prod="",_xlpm.Prod=0), IF(_xlpm.Status="ATIVO",0,_xlpm.Status), _xlpm.Prod ) ), "")} -> 1 | T62: {=IFERROR( _xlfn.LET( _xlpm.Prod,INDEX(Din!$J$4:$AR$1000, MATCH($L62,Din!$I$4:$I$1000,0), MATCH(T$6,Din!$J$3:$AO$3,0)), _xlpm.Status,INDEX('FORÇA DE TRABALHO'!$E$15:$E$999, MATCH($L62,'FORÇA DE TRABALHO'!$C$15:$C$999,0), MATCH(T$6+0,'FORÇA DE TRABALHO'!$E$14:$E$14+0,0)), IF( OR(_xlpm.Prod="",_xlpm.Prod=0), IF(_xlpm.Status="ATIVO",0,_xlpm.Status), _xlpm.Prod ) ), "")} | ... AQ62: {=IFERROR( _xlfn.LET( _xlpm.Prod,INDEX(Din!$J$4:$AR$1000, MATCH($L62,Din!$I$4:$I$1000,0), MATCH(AQ$6,Din!$J$3:$AO$3,0)), _xlpm.Status,INDEX('FORÇA DE TRABALHO'!$E$15:$E$999, MATCH($L62,'FORÇA DE TRABALHO'!$C$15:$C$999,0), MATCH(AQ$6+0,'FORÇA DE TRABALHO'!$E$14:$E$14+0,0)), IF( OR(_xlpm.Prod="",_xlpm.Prod=0), IF(_xlpm.Status="ATIVO",0,_xlpm.Status), _xlpm.Prod ) ), "")}

Sheet BASE TOA
A1: Mês | B1: Data_Padronizada | C1: Dia Semana | D1: Coordenador | E1: Resumo TIPO | F1: Tempo de atendimento | G1: SLA | H1: Classificação técnica | I1: Supervisor | J1: Recurso | K1: Número da OS | L1: Designador de Acesso | M1: Janela de serviço | N1: ID atividade | O1: iTASK | P1: RITM | Q1: Número da Ordem | R1: Tipo | S1: Intervalo de Tempo | T1: Status da Atividade | U1: Código de Cliente | V1: Nome | W1: Endereço | X1: Complemento | Y1: Cidade | Z1: Estado | AA1: CEP | AB1: Zona de trabalho | AC1: Habilidade de Trabalho | AD1: Início | AE1: Fim | AF1: Duração | AG1: SLA final | AH1: SLA início | AI1: ID do Armário | AJ1: Porta GPON | AK1: CTO | AL1: CSO | AM1: Início Real | AN1: Protocolo 1 | AO1: Quantidade de pontos IPTV | AP1: Código de Localização | AQ1: Escritório de Serviço | AR1: Área Telefônica | AS1: Data Agendada | AT1: Usuário Final | AU1: Janela de entrega | AV1: Código de Resultado do Exame | AW1: Segmento do Cliente | AX1: Geo Segmento | AY1: Classe do Serviço | AZ1: Código de atuação | BA1: Razão de Cancelamento | BB1: Data da Criação do Acionamento | BC1: Motivo da Pendência | BD1: Data de Criação da Ordem | BE1: Horário de encerramento 1 | BF1: Código de Encerramento 1 | BG1: Razão da Reclamação | BH1: Status da Coordenada | BI1: Número do Terminal Ponta A | BJ1: Usuário Conclusão Atividade | BK1: Criação de atividade | BL1: Atribuição da atividade | BM1: Inventário instalado em AT | BN1: Nome Contato | BO1: Telefone Contato | BP1: Data | BQ1: Início - Fim | BR1: Primeira Operação Manual Executada por Usuário (Nome) | BS1: Código | BT1: XA_NOT_DONE_CONTEXT_POC | BU1: XA_NOT_DONE_REASON_POC | BV1: Contrato da Empresa | BW1: Nome da Empresa
A2: =CONCATENATE(MONTH(Base[[#This Row],[Data_Padronizada]]),"/",YEAR(Base[[#This Row],[Data_Padronizada]]))*1 -> 1 | B2: {=IF(ISTEXT(BP2), IFERROR(VALOR.DATA(TRIM(BP2)), VALUE(TRIM(BP2))), BP2)} -> 0 | C2: =TEXT(Base[[#This Row],[Data_Padronizada]],"DDD") -> sáb | D2: =_xlfn.XLOOKUP(Base[[#This Row],[Recurso]],'DE-PARA'!$A$1:$A$1000,'DE-PARA'!$D$1:$D$1000) -> 0 | E2: =_xlfn.XLOOKUP(Base[[#This Row],[Tipo]],'DE-PARA'!$K$2:$K$63,'DE-PARA'!$L$2:$L$63,"Fazer De-Para") -> Fazer De-Para | F2: =Base[[#This Row],[Duração]]*24 -> 0 | G2: =HOUR(Base[[#This Row],[Tempo de atendimento]]/24) -> 0 | H2: =_xlfn.XLOOKUP(Base[[#This Row],[Recurso]],'DE-PARA'!$A$1:$A$1000,'DE-PARA'!$E$1:$E$1000) -> 0 | I2: =_xlfn.XLOOKUP(Base[[#This Row],[Recurso]],'DE-PARA'!$A$1:$A$1000,'DE-PARA'!$F$1:$F$1000) -> 0
A3: =CONCATENATE(MONTH(Base[[#This Row],[Data_Padronizada]]),"/",YEAR(Base[[#This Row],[Data_Padronizada]]))*1 -> 1 | B3: {=IF(ISTEXT(BP3), IFERROR(VALOR.DATA(TRIM(BP3)), VALUE(TRIM(BP3))), BP3)} -> 0 | C3: =TEXT(Base[[#This Row],[Data_Padronizada]],"DDD") -> sáb | D3: =_xlfn.XLOOKUP(Base[[#This Row],[Recurso]],'DE-PARA'!$A$1:$A$1000,'DE-PARA'!$D$1:$D$1000) -> 0 | E3: =_xlfn.XLOOKUP(Base[[#This Row],[Tipo]],'DE-PARA'!$K$2:$K$63,'DE-PARA'!$L$2:$L$63,"Fazer De-Para") -> Fazer De-Para | F3: =Base[[#This Row],[Duração]]*24 -> 0 | G3: =HOUR(Base[[#This Row],[Tempo de atendimento]]/24) -> 0 | H3: =_xlfn.XLOOKUP(Base[[#This Row],[Recurso]],'DE-PARA'!$A$1:$A$1000,'DE-PARA'!$E$1:$E$1000) -> 0 | I3: =_xlfn.XLOOKUP(Base[[#This Row],[Recurso]],'DE-PARA'!$A$1:$A$1000,'DE-PARA'!$F$1:$F$1000) -> 0
A4: =CONCATENATE(MONTH(Base[[#This Row],[Data_Padronizada]]),"/",YEAR(Base[[#This Row],[Data_Padronizada]]))*1 -> 1 | B4: {=IF(ISTEXT(BP4), IFERROR(VALOR.DATA(TRIM(BP4)), VALUE(TRIM(BP4))), BP4)} -> 0 | C4: =TEXT(Base[[#This Row],[Data_Padronizada]],"DDD") -> sáb | D4: =_xlfn.XLOOKUP(Base[[#This Row],[Recurso]],'DE-PARA'!$A$1:$A$1000,'DE-PARA'!$D$1:$D$1000) -> 0 | E4: =_xlfn.XLOOKUP(Base[[#This Row],[Tipo]],'DE-PARA'!$K$2:$K$63,'DE-PARA'!$L$2:$L$63,"Fazer De-Para") -> Fazer De-Para | F4: =Base[[#This Row],[Duração]]*24 -> 0 | G4: =HOUR(Base[[#This Row],[Tempo de atendimento]]/24) -> 0 | H4: =_xlfn.XLOOKUP(Base[[#This Row],[Recurso]],'DE-PARA'!$A$1:$A$1000,'DE-PARA'!$E$1:$E$1000) -> 0 | I4: =_xlfn.XLOOKUP(Base[[#This Row],[Recurso]],'DE-PARA'!$A$1:$A$1000,'DE-PARA'!$F$1:$F$1000) -> 0
A5: =CONCATENATE(MONTH(Base[[#This Row],[Data_Padronizada]]),"/",YEAR(Base[[#This Row],[Data_Padronizada]]))*1 -> 1 | B5: {=IF(ISTEXT(BP5), IFERROR(VALOR.DATA(TRIM(BP5)), VALUE(TRIM(BP5))), BP5)} -> 0 | C5: =TEXT(Base[[#This Row],[Data_Padronizada]],"DDD") -> sáb | D5: =_xlfn.XLOOKUP(Base[[#This Row],[Recurso]],'DE-PARA'!$A$1:$A$1000,'DE-PARA'!$D$1:$D$1000) -> 0 | E5: =_xlfn.XLOOKUP(Base[[#This Row],[Tipo]],'DE-PARA'!$K$2:$K$63,'DE-PARA'!$L$2:$L$63,"Fazer De-Para") -> Fazer De-Para | F5: =Base[[#This Row],[Duração]]*24 -> 0 | G5: =HOUR(Base[[#This Row],[Tempo de atendimento]]/24) -> 0 | H5: =_xlfn.XLOOKUP(Base[[#This Row],[Recurso]],'DE-PARA'!$A$1:$A$1000,'DE-PARA'!$E$1:$E$1000) -> 0 | I5: =_xlfn.XLOOKUP(Base[[#This Row],[Recurso]],'DE-PARA'!$A$1:$A$1000,'DE-PARA'!$F$1:$F$1000) -> 0
A6: =CONCATENATE(MONTH(Base[[#This Row],[Data_Padronizada]]),"/",YEAR(Base[[#This Row],[Data_Padronizada]]))*1 -> 1 | B6: {=IF(ISTEXT(BP6), IFERROR(VALOR.DATA(TRIM(BP6)), VALUE(TRIM(BP6))), BP6)} -> 0 | C6: =TEXT(Base[[#This Row],[Data_Padronizada]],"DDD") -> sáb | D6: =_xlfn.XLOOKUP(Base[[#This Row],[Recurso]],'DE-PARA'!$A$1:$A$1000,'DE-PARA'!$D$1:$D$1000) -> 0 | E6: =_xlfn.XLOOKUP(Base[[#This Row],[Tipo]],'DE-PARA'!$K$2:$K$63,'DE-PARA'!$L$2:$L$63,"Fazer De-Para") -> Fazer De-Para | F6: =Base[[#This Row],[Duração]]*24 -> 0 | G6: =HOUR(Base[[#This Row],[Tempo de atendimento]]/24) -> 0 | H6: =_xlfn.XLOOKUP(Base[[#This Row],[Recurso]],'DE-PARA'!$A$1:$A$1000,'DE-PARA'!$E$1:$E$1000) -> 0 | I6: =_xlfn.XLOOKUP(Base[[#This Row],[Recurso]],'DE-PARA'!$A$1:$A$1000,'DE-PARA'!$F$1:$F$1000) -> 0
A7: =CONCATENATE(MONTH(Base[[#This Row],[Data_Padronizada]]),"/",YEAR(Base[[#This Row],[Data_Padronizada]]))*1 -> 1 | B7: {=IF(ISTEXT(BP7), IFERROR(VALOR.DATA(TRIM(BP7)), VALUE(TRIM(BP7))), BP7)} -> 0 | C7: =TEXT(Base[[#This Row],[Data_Padronizada]],"DDD") -> sáb | D7: =_xlfn.XLOOKUP(Base[[#This Row],[Recurso]],'DE-PARA'!$A$1:$A$1000,'DE-PARA'!$D$1:$D$1000) -> 0 | E7: =_xlfn.XLOOKUP(Base[[#This Row],[Tipo]],'DE-PARA'!$K$2:$K$63,'DE-PARA'!$L$2:$L$63,"Fazer De-Para") -> Fazer De-Para | F7: =Base[[#This Row],[Duração]]*24 -> 0 | G7: =HOUR(Base[[#This Row],[Tempo de atendimento]]/24) -> 0 | H7: =_xlfn.XLOOKUP(Base[[#This Row],[Recurso]],'DE-PARA'!$A$1:$A$1000,'DE-PARA'!$E$1:$E$1000) -> 0 | I7: =_xlfn.XLOOKUP(Base[[#This Row],[Recurso]],'DE-PARA'!$A$1:$A$1000,'DE-PARA'!$F$1:$F$1000) -> 0
A8: =CONCATENATE(MONTH(Base[[#This Row],[Data_Padronizada]]),"/",YEAR(Base[[#This Row],[Data_Padronizada]]))*1 -> 1 | B8: {=IF(ISTEXT(BP8), IFERROR(VALOR.DATA(TRIM(BP8)), VALUE(TRIM(BP8))), BP8)} -> 0 | C8: =TEXT(Base[[#This Row],[Data_Padronizada]],"DDD") -> sáb | D8: =_xlfn.XLOOKUP(Base[[#This Row],[Recurso]],'DE-PARA'!$A$1:$A$1000,'DE-PARA'!$D$1:$D$1000) -> 0 | E8: =_xlfn.XLOOKUP(Base[[#This Row],[Tipo]],'DE-PARA'!$K$2:$K$63,'DE-PARA'!$L$2:$L$63,"Fazer De-Para") -> Fazer De-Para | F8: =Base[[#This Row],[Duração]]*24 -> 0 | G8: =HOUR(Base[[#This Row],[Tempo de atendimento]]/24) -> 0 | H8: =_xlfn.XLOOKUP(Base[[#This Row],[Recurso]],'DE-PARA'!$A$1:$A$1000,'DE-PARA'!$E$1:$E$1000) -> 0 | I8: =_xlfn.XLOOKUP(Base[[#This Row],[Recurso]],'DE-PARA'!$A$1:$A$1000,'DE-PARA'!$F$1:$F$1000) -> 0
A9: =CONCATENATE(MONTH(Base[[#This Row],[Data_Padronizada]]),"/",YEAR(Base[[#This Row],[Data_Padronizada]]))*1 -> 1 | B9: {=IF(ISTEXT(BP9), IFERROR(VALOR.DATA(TRIM(BP9)), VALUE(TRIM(BP9))), BP9)} -> 0 | C9: =TEXT(Base[[#This Row],[Data_Padronizada]],"DDD") -> sáb | D9: =_xlfn.XLOOKUP(Base[[#This Row],[Recurso]],'DE-PARA'!$A$1:$A$1000,'DE-PARA'!$D$1:$D$1000) -> 0 | E9: =_xlfn.XLOOKUP(Base[[#This Row],[Tipo]],'DE-PARA'!$K$2:$K$63,'DE-PARA'!$L$2:$L$63,"Fazer De-Para") -> Fazer De-Para | F9: =Base[[#This Row],[Duração]]*24 -> 0 | G9: =HOUR(Base[[#This Row],[Tempo de atendimento]]/24) -> 0 | H9: =_xlfn.XLOOKUP(Base[[#This Row],[Recurso]],'DE-PARA'!$A$1:$A$1000,'DE-PARA'!$E$1:$E$1000) -> 0 | I9: =_xlfn.XLOOKUP(Base[[#This Row],[Recurso]],'DE-PARA'!$A$1:$A$1000,'DE-PARA'!$F$1:$F$1000) -> 0
A10: =CONCATENATE(MONTH(Base[[#This Row],[Data_Padronizada]]),"/",YEAR(Base[[#This Row],[Data_Padronizada]]))*1 -> 1 | B10: {=IF(ISTEXT(BP10), IFERROR(VALOR.DATA(TRIM(BP10)), VALUE(TRIM(BP10))), BP10)} -> 0 | C10: =TEXT(Base[[#This Row],[Data_Padronizada]],"DDD") -> sáb | D10: =_xlfn.XLOOKUP(Base[[#This Row],[Recurso]],'DE-PARA'!$A$1:$A$1000,'DE-PARA'!$D$1:$D$1000) -> 0 | E10: =_xlfn.XLOOKUP(Base[[#This Row],[Tipo]],'DE-PARA'!$K$2:$K$63,'DE-PARA'!$L$2:$L$63,"Fazer De-Para") -> Fazer De-Para | F10: =Base[[#This Row],[Duração]]*24 -> 0 | G10: =HOUR(Base[[#This Row],[Tempo de atendimento]]/24) -> 0 | H10: =_xlfn.XLOOKUP(Base[[#This Row],[Recurso]],'DE-PARA'!$A$1:$A$1000,'DE-PARA'!$E$1:$E$1000) -> 0 | I10: =_xlfn.XLOOKUP(Base[[#This Row],[Recurso]],'DE-PARA'!$A$1:$A$1000,'DE-PARA'!$F$1:$F$1000) -> 0
A11: =CONCATENATE(MONTH(Base[[#This Row],[Data_Padronizada]]),"/",YEAR(Base[[#This Row],[Data_Padronizada]]))*1 -> 1 | B11: {=IF(ISTEXT(BP11), IFERROR(VALOR.DATA(TRIM(BP11)), VALUE(TRIM(BP11))), BP11)} -> 0 | C11: =TEXT(Base[[#This Row],[Data_Padronizada]],"DDD") -> sáb | D11: =_xlfn.XLOOKUP(Base[[#This Row],[Recurso]],'DE-PARA'!$A$1:$A$1000,'DE-PARA'!$D$1:$D$1000) -> 0 | E11: =_xlfn.XLOOKUP(Base[[#This Row],[Tipo]],'DE-PARA'!$K$2:$K$63,'DE-PARA'!$L$2:$L$63,"Fazer De-Para") -> Fazer De-Para | F11: =Base[[#This Row],[Duração]]*24 -> 0 | G11: =HOUR(Base[[#This Row],[Tempo de atendimento]]/24) -> 0 | H11: =_xlfn.XLOOKUP(Base[[#This Row],[Recurso]],'DE-PARA'!$A$1:$A$1000,'DE-PARA'!$E$1:$E$1000) -> 0 | I11: =_xlfn.XLOOKUP(Base[[#This Row],[Recurso]],'DE-PARA'!$A$1:$A$1000,'DE-PARA'!$F$1:$F$1000) -> 0
A12: =CONCATENATE(MONTH(Base[[#This Row],[Data_Padronizada]]),"/",YEAR(Base[[#This Row],[Data_Padronizada]]))*1 -> 1 | B12: {=IF(ISTEXT(BP12), IFERROR(VALOR.DATA(TRIM(BP12)), VALUE(TRIM(BP12))), BP12)} -> 0 | C12: =TEXT(Base[[#This Row],[Data_Padronizada]],"DDD") -> sáb | D12: =_xlfn.XLOOKUP(Base[[#This Row],[Recurso]],'DE-PARA'!$A$1:$A$1000,'DE-PARA'!$D$1:$D$1000) -> 0 | E12: =_xlfn.XLOOKUP(Base[[#This Row],[Tipo]],'DE-PARA'!$K$2:$K$63,'DE-PARA'!$L$2:$L$63,"Fazer De-Para") -> Fazer De-Para | F12: =Base[[#This Row],[Duração]]*24 -> 0 | G12: =HOUR(Base[[#This Row],[Tempo de atendimento]]/24) -> 0 | H12: =_xlfn.XLOOKUP(Base[[#This Row],[Recurso]],'DE-PARA'!$A$1:$A$1000,'DE-PARA'!$E$1:$E$1000) -> 0 | I12: =_xlfn.XLOOKUP(Base[[#This Row],[Recurso]],'DE-PARA'!$A$1:$A$1000,'DE-PARA'!$F$1:$F$1000) -> 0
A13: =CONCATENATE(MONTH(Base[[#This Row],[Data_Padronizada]]),"/",YEAR(Base[[#This Row],[Data_Padronizada]]))*1 -> 1 | B13: {=IF(ISTEXT(BP13), IFERROR(VALOR.DATA(TRIM(BP13)), VALUE(TRIM(BP13))), BP13)} -> 0 | C13: =TEXT(Base[[#This Row],[Data_Padronizada]],"DDD") -> sáb | D13: =_xlfn.XLOOKUP(Base[[#This Row],[Recurso]],'DE-PARA'!$A$1:$A$1000,'DE-PARA'!$D$1:$D$1000) -> 0 | E13: =_xlfn.XLOOKUP(Base[[#This Row],[Tipo]],'DE-PARA'!$K$2:$K$63,'DE-PARA'!$L$2:$L$63,"Fazer De-Para") -> Fazer De-Para | F13: =Base[[#This Row],[Duração]]*24 -> 0 | G13: =HOUR(Base[[#This Row],[Tempo de atendimento]]/24) -> 0 | H13: =_xlfn.XLOOKUP(Base[[#This Row],[Recurso]],'DE-PARA'!$A$1:$A$1000,'DE-PARA'!$E$1:$E$1000) -> 0 | I13: =_xlfn.XLOOKUP(Base[[#This Row],[Recurso]],'DE-PARA'!$A$1:$A$1000,'DE-PARA'!$F$1:$F$1000) -> 0
... A2682: =CONCATENATE(MONTH(Base[[#This Row],[Data_Padronizada]]),"/",YEAR(Base[[#This Row],[Data_Padronizada]]))*1 -> 1 | B2682: {=IF(ISTEXT(BP2682), IFERROR(VALOR.DATA(TRIM(BP2682)), VALUE(TRIM(BP2682))), BP2682)} -> 0 | C2682: =TEXT(Base[[#This Row],[Data_Padronizada]],"DDD") -> sáb | D2682: =_xlfn.XLOOKUP(Base[[#This Row],[Recurso]],'DE-PARA'!$A$1:$A$1000,'DE-PARA'!$D$1:$D$1000) -> 0 | E2682: =_xlfn.XLOOKUP(Base[[#This Row],[Tipo]],'DE-PARA'!$K$2:$K$63,'DE-PARA'!$L$2:$L$63,"Fazer De-Para") -> Fazer De-Para | F2682: =Base[[#This Row],[Duração]]*24 -> 0 | G2682: =HOUR(Base[[#This Row],[Tempo de atendimento]]/24) -> 0 | H2682: =_xlfn.XLOOKUP(Base[[#This Row],[Recurso]],'DE-PARA'!$A$1:$A$1000,'DE-PARA'!$E$1:$E$1000) -> 0 | I2682: =_xlfn.XLOOKUP(Base[[#This Row],[Recurso]],'DE-PARA'!$A$1:$A$1000,'DE-PARA'!$F$1:$F$1000) -> 0

Sheet DE-PARA
A1: Nome | B1: ÁREA ORIGEM | C1: UF | D1: COORD | E1: CLASSIFICACAO | F1: Supervisor | K1: Tipo | L1: Tipo_Padronizado | Q1: Tipo | R1: Tipo_Padronizado
A2: GLAUBER ARAUJO SANTOS | B2: B2B VIVO | C2: BA | D2: WEDSON FERNANDES DA SILVA | E2: SUPERVISOR | F2: Wedson | K2: Almoxarifado | L2: Interno | Q2: Defeito Banda Larga | R2: Reparo
A3: ADÉCIO JÂNIO PEREIRA DE SOUSA | B3: B2B VIVO | C3: CE | D3: DIEGO SOARES LOPES | E3: TECNICO TX | F3: Rafael Silva | K3: Ampliação Equipamento | L3: OUTRAS | Q3: Instalação / Adequação de Cliente em Caixa de Conexão (B2B) | R3: Construção
A4: CARLOS EDUARDO DA SILVA QUEIROZ | B4: B2B VIVO | C4: CE | D4: DIEGO SOARES LOPES | E4: TECNICO TX | F4: Rafael Silva | K4: Ativação Porta Switch | L4: OUTRAS | Q4: Instalação / Adequação de DROP Cliente (B2B) | R4: Construção
A5: ELIAS PEREIRA PASSOS FILHO | B5: MOIN B2C | C5: CE | D5: DIEGO SOARES LOPES | E5: TECNICO REDE EXTERNA | F5: Rafael Silva | K5: Ativação Porta Switch Router | L5: OUTRAS | Q5: Instalação Banda | R5: Ativação
A6: FRANCISCO EDVALDO CARDOSO CARNEIRO | B6: B2B VIVO | C6: CE | D6: DIEGO SOARES LOPES | E6: TECNICO TX | F6: Rafael Silva | K6: Atividade Móvel | L6: OUTRAS | Q6: Instalação Banda Larga Avulsa | R6: Ativação
A7: Janecleyton Ricardo Juca | B7: MOIN B2C | C7: CE | D7: DIEGO SOARES LOPES | E7: TECNICO REDE EXTERNA | F7: Rafael Silva | K7: Backbone | L7: Melhoria | Q7: Migração de Clientes B2B | R7: Melhoria
A8: JEAN GALVÃO OLIVEIRA | B8: B2B VIVO | C8: CE | D8: DIEGO SOARES LOPES | E8: TECNICO TX | F8: Rafael Silva | K8: Checklist | L8: Interno | Q8: Monousuário DROP B2B
A9: CARLOS EDUARDO DA SILVA | B9: B2B VIVO | C9: RN | D9: DIEGO SOARES LOPES | E9: TECNICO TX | F9: Rafael Silva | K9: Desconexão de Serviços | L9: Desconexão | Q9: Refeição120 | R9: Interno
A10: Adailton Dos Santos | B10: B2B VIVO | C10: BA | D10: WEDSON FERNANDES DA SILVA | E10: TECNICO TX | F10: Rafael Brandão | K10: Desconexão Fibra | L10: Desconexão | Q10: Refeição60 | R10: Interno
A11: ANDERSON COSTA DOS SANTOS | B11: MOIN B2C | C11: BA | D11: WEDSON FERNANDES DA SILVA | E11: TECNICO REDE EXTERNA | F11: Rafael Brandão | K11: Desinstalação Equipamento | L11: Desconexão | Q11: Refeição90 | R11: Interno
A12: CARLOS FRANCISCO DOS SANTOS | B12: B2B VIVO | C12: BA | D12: WEDSON FERNANDES DA SILVA | E12: TECNICO TX | F12: Rafael Brandão | K12: Exame Periódico | L12: Interno | Q12: Reunião Interna | R12: Interno
A13: EDILSON BOMFIM QUEIROZ | B13: B2B VIVO | C13: BA | D13: WEDSON FERNANDES DA SILVA | E13: TECNICO TX | F13: Rafael Brandão | K13: Facilidade GPON | L13: OUTRAS | Q13: Teste Óptico Cliente (B2B) em Caixa Conexão
A14: MOISES SANTOS BUISINE | B14: MOIN B2C | C14: BA | D14: WEDSON FERNANDES DA SILVA | E14: TECNICO REDE EXTERNA | F14: Rafael Brandão | K14: Infra ARD | L14: OUTRAS | Q14: Troca de Cabo
A15: TALITA WEDJA FELIPE DA SILVA | B15: B2B VIVO | C15: BA | D15: WEDSON FERNANDES DA SILVA | E15: TECNICO REDE EXTERNA | F15: Rafael Brandão | K15: Infra ARD CORP | L15: OUTRAS | Q15: Vistoria em rede de Backbone
A16: HUGO PEREIRA LEMOS | C16: BA | D16: WEDSON FERNANDES DA SILVA | E16: TECNICO TX | F16: Rafael Brandão | K16: INS Melhoria | L16: Melhoria
A17: JHONATAN MONTEIRO DE ANDRADE | C17: BA | D17: WEDSON FERNANDES DA SILVA | E17: TECNICO TX | F17: Rafael Brandão | K17: INS Rede Lançamento | L17: Construção
A18: JOAO ALBERTO MENDES GUEDES | C18: BA | D18: WEDSON FERNANDES DA SILVA | E18: TECNICO REDE EXTERNA | F18: Rafael Brandão | K18: INS SDWAN | L18: Instalação
A19: LUCAS DOS SANTOS COELHO | C19: BA | D19: WEDSON FERNANDES DA SILVA | E19: TECNICO REDE EXTERNA | F19: Rafael Brandão | K19: Instalação ARD Novo | L19: OUTRAS
A20: MARCIO DE SOUSA LIMA | C20: BA | D20: WEDSON FERNANDES DA SILVA | E20: TECNICO TX | F20: Rafael Brandão | K20: Instalação Dados | L20: Instalação
A21: VALDEILTON DE SOUZA DO NASCIMENTO | D21: WEDSON FERNANDES DA SILVA | E21: TECNICO REDE EXTERNA | F21: Rafael Brandão | K21: Instalação Dados Roteador | L21: Instalação
A22: HELIO SANDRO MONTEIRO PEIXOTO | B22: B2B VIVO | C22: PE | D22: RICARDO ALVES DOS SANTOS | E22: TECNICO TX | F22: Marcos Antonio Nogueira | K22: Instalação DDR | L22: Instalação
A23: JOSE ALVES DE SOUZA JUNIOR | B23: B2B VIVO | C23: PE | D23: RICARDO ALVES DOS SANTOS | E23: TECNICO TX | F23: Marcos Antonio Nogueira | K23: Instalação Internet X | L23: Instalação
A24: JOSE WILSON GOMES DA SILVA | B24: B2B VIVO | C24: PE | D24: RICARDO ALVES DOS SANTOS | E24: TECNICO TX | F24: Marcos Antonio Nogueira | K24: Instalação Internet X Light | L24: Instalação
A25: LUCIANO RODRIGUES FARIAS DA SILVA | B25: MOIN B2C | C25: PE | D25: RICARDO ALVES DOS SANTOS | E25: TECNICO REDE EXTERNA | F25: Marcos Antonio Nogueira | K25: Instalação Roteador | L25: Instalação
A26: SEVERINO INOCENCIO PEDROZA FILHO | B26: MOIN B2C | C26: PE | D26: RICARDO ALVES DOS SANTOS | E26: TECNICO REDE EXTERNA | F26: Marcos Antonio Nogueira | K26: Instalação SIP | L26: Instalação
A27: TIAGO GUEDES DOS SANTOS | B27: B2B VIVO | C27: PE | D27: RICARDO ALVES DOS SANTOS | E27: TECNICO TX | F27: Marcos Antonio Nogueira | K27: Manutenção Corretiva | L27: Reparo
A28: ALEXANDRE BORGES DA SILVA | B28: MOIN B2C | C28: PE | D28: RICARDO ALVES DOS SANTOS | E28: TECNICO REDE EXTERNA | F28: Leonardo Oliveira | K28: Manutenção de Veículo | L28: Interno
A29: EDMILSON HONORATO DE SANTANA JUNIOR | C29: PE | D29: RICARDO ALVES DOS SANTOS | E29: TECNICO REDE EXTERNA | F29: Leonardo Oliveira | K29: Manutenção Preventiva | L29: Reparo
A30: GEORGE MENEZES DOS SANTOS | B30: B2B VIVO | C30: SE | D30: WEDSON FERNANDES DA SILVA | E30: TECNICO TX | F30: Jomilson Barros | K30: Migração de Acesso | L30: Melhoria
A31: JOSE WELLINTON SOUZA SILVA | B31: B2B VIVO | C31: SE | D31: WEDSON FERNANDES DA SILVA | E31: TECNICO TX | F31: Jomilson Barros | K31: Migração de rede | L31: Melhoria
A32: ALDIR GOES DOS SANTOS | B32: B2B VIVO | C32: BA | D32: WEDSON FERNANDES DA SILVA | E32: TECNICO TX | F32: Glauber Araujo | K32: Migração SW | L32: OUTRAS
A33: CARLOS ANDRE SANTOS LIMA | B33: B2B VIVO | C33: BA | D33: WEDSON FERNANDES DA SILVA | E33: TECNICO TX | F33: Glauber Araujo | K33: Migração Transmissão | L33: Melhoria
A34: LAISE BRITO BOTELHO | B34: MOIN B2C | C34: BA | D34: WEDSON FERNANDES DA SILVA | E34: TECNICO REDE EXTERNA | F34: Glauber Araujo | K34: Planta Interna | L34: Interno
A35: RICARDO SILVA DE DEUS | B35: B2B VIVO | C35: BA | D35: WEDSON FERNANDES DA SILVA | E35: TECNICO TX | F35: Glauber Araujo | K35: Porta Switch/Router | L35: OUTRAS
A36: SANDRA GABRIELA DOS ANJOS BARBOSA | B36: B2B VIVO | C36: BA | D36: WEDSON FERNANDES DA SILVA | E36: TECNICO TX | F36: Glauber Araujo | K36: Pré-Ins | L36: OUTRAS
A37: THIAGO PEREIRA LIMA | B37: MOIN B2C | C37: BA | D37: WEDSON FERNANDES DA SILVA | E37: TECNICO REDE EXTERNA | F37: Glauber Araujo | K37: Preventiva CORP | L37: Reparo
A38: GILSON PATROCINIO DOS SANTOS ALENCAR | C38: PE | D38: RICARDO ALVES DOS SANTOS | E38: TECNICO REDE EXTERNA | F38: Glauber Araujo | K38: Refeição | L38: Interno
A39: ALANA FERREIRA DE LIMA | B39: MOIN B2C | C39: PB | D39: RICARDO ALVES DOS SANTOS | E39: TECNICO REDE EXTERNA | F39: Denys Carvalho | K39: Refeição I | L39: Refeição
A40: ANTONIO GALDINO DA SILVA NETO | B40: B2B VIVO | C40: PB | D40: RICARDO ALVES DOS SANTOS | E40: TECNICO TX | F40: Denys Carvalho | K40: Reparo Dados | L40: Reparo
A41: DANILO COSTA CASSEMIRO DA SILVA | B41: MOIN B2C | C41: PB | D41: RICARDO ALVES DOS SANTOS | E41: TECNICO REDE EXTERNA | F41: Denys Carvalho | K41: Reparo DDR | L41: Reparo
A42: JOAO FRANCISCO DE BRITO UCHOA | B42: MOIN B2C | C42: PB | D42: RICARDO ALVES DOS SANTOS | E42: TECNICO REDE EXTERNA | F42: Denys Carvalho | K42: Reparo OSP | L42: Reparo OSP
A43: JONATA GOMES DE SOUZA | B43: B2B VIVO | C43: PB | D43: RICARDO ALVES DOS SANTOS | E43: TECNICO REDE EXTERNA | F43: Denys Carvalho | K43: Reparo Rede | L43: REPARO
A44: JOSE AVELINO DE QUEIROZ NETO | B44: B2B VIVO | C44: PB | D44: RICARDO ALVES DOS SANTOS | E44: TECNICO TX | F44: Denys Carvalho | K44: Reparo Roteador | L44: Reparo
A45: JONATA GOMES DE SOUZA | C45: PB | D45: RICARDO ALVES DOS SANTOS | E45: TECNICO REDE EXTERNA | F45: Denys Carvalho | K45: REQ Atividade | L45: OUTRAS
A46: PEDRO ARTHUR ALMEIDA CARTAXO | D46: RICARDO ALVES DOS SANTOS | E46: TECNICO REDE EXTERNA | F46: Denys Carvalho | K46: Retirada Dados | L46: Desconexão
A47: WILTON BRAGA DA SILVA | B47: B2B VIVO | C47: AL | D47: RICARDO ALVES DOS SANTOS | E47: TECNICO TX | F47: Carlos Henrique | K47: Retirada Dados Roteador | L47: Desconexão
A48: HUMBERTO DOUGLAS ARAUJO SANTOS | C48: AL | D48: RICARDO ALVES DOS SANTOS | E48: TECNICO TX | F48: Carlos Henrique | K48: Retirada DDR | L48: Desconexão
A49: JAIRON VIEIRA ALVES | B49: MOIN B2C | C49: PI | D49: DIEGO SOARES LOPES | E49: TECNICO REDE EXTERNA | F49: Carlos Eduardo | K49: Retirada Roteador | L49: Desconexão
A50: EBER BORGES DE SOUZA | B50: B2B VIVO | C50: RN | D50: DIEGO SOARES LOPES | E50: TECNICO TX | F50: Carlos Eduardo | K50: Reunião | L50: Interno
A51: RAFAELA ALVES FACUNDO | B51: MOIN B2C | C51: CE | D51: DIEGO SOARES LOPES | E51: TECNICO REDE EXTERNA | F51: Anderson Morais | K51: Serviço Dados | L51: OUTRAS
A52: Wenderson da costa barbosa | B52: MOIN B2C | C52: CE | D52: DIEGO SOARES LOPES | E52: TECNICO REDE EXTERNA | F52: Anderson Morais | K52: SWT Comissionamento | L52: OUTRAS
A53: FRANCY ANA ALEXANDRINO CLAUDIO | C53: CE | D53: DIEGO SOARES LOPES | E53: TECNICO TX | F53: Anderson Morais | K53: Teste de Rede | L53: OUTRAS
A54: SILVIA JOELIA DE SOUSA GUIMARAES | C54: CE | D54: DIEGO SOARES LOPES | E54: TECNICO REDE EXTERNA | F54: Anderson Morais | K54: Testes | L54: Vistoria
A55: EDSON TAVARES DA SILVA JUNIOR | B55: B2B VIVO | C55: PE | D55: RICARDO ALVES DOS SANTOS | E55: TECNICO TX | F55: Alan da Silva | K55: Testes de Portas | L55: Vistoria
A56: FERNANDO PINHEIRO DA SILVA JUNIOR | B56: B2B VIVO | C56: PE | D56: RICARDO ALVES DOS SANTOS | E56: TECNICO TX | F56: Alan da Silva | K56: Treinamento | L56: Interno
A57: Luciano Miguel Da Silva | B57: B2B VIVO | C57: PE | D57: RICARDO ALVES DOS SANTOS | E57: TECNICO TX | F57: Alan da Silva | K57: Viabilidade Técnica | L57: OUTRAS
A58: PAULO ROBERTO DA SILVA | B58: B2B VIVO | C58: PE | D58: RICARDO ALVES DOS SANTOS | E58: TECNICO REDE EXTERNA | F58: Alan da Silva | K58: Vistoria | L58: Vistoria
A59: ADRIANO PINHEIRO CARDOSO | B59: B2B VIVO | C59: BA | D59: WEDSON FERNANDES DA SILVA | K59: Vistoria BBN | L59: Vistoria
A60: CINTHIA KARDILANE CARVALHO DOS SANTOS CALADO | B60: B2B VIVO | C60: PE | D60: RICARDO ALVES DOS SANTOS | K60: Vistoria CORP | L60: Vistoria
A61: EDVALDO TEIXEIRA BATISTA JUNIOR | B61: B2B VIVO | C61: BA | D61: WEDSON FERNANDES DA SILVA | K61: Vistoria VIVO | L61: Vistoria
A62: FABRICIO BARBOSA DE OLIVEIRA ANDRADE | B62: MOIN B2C | C62: PB | D62: RICARDO ALVES DOS SANTOS | K62: Vistoria VIVO | L62: Vistoria
A63: FRANCISCO CARNEIRO | B63: B2B VIVO | C63: CE | D63: DIEGO SOARES LOPES | K63: Apoio Técnico | L63: Melhoria
A64: JONATA MONTEIRO DE ANDRADE | B64: B2B VIVO | C64: BA | D64: WEDSON FERNANDES DA SILVA
A65: JULIANA DE FREITAS MENDES | B65: MOIN B2C | C65: CE | D65: DIEGO SOARES LOPES
A66: KARINE FERREIRA SANTANA | B66: MOIN B2C | C66: BA | D66: WEDSON FERNANDES DA SILVA
A67: LUIZ BARRETO NOBRE NETO | B67: MOIN B2C | C67: BA | D67: WEDSON FERNANDES DA SILVA
A68: ROBERTO SOARES DE BRITO | B68: MOIN B2C | C68: PE | D68: RICARDO ALVES DOS SANTOS
A69: RUBEVALDO DE ARAUJO OLIVEIRA | B69: B2B VIVO | C69: BA | D69: WEDSON FERNANDES DA SILVA
A70: Silvia Joelia de Sousa Guimarães | B70: B2B VIVO | C70: CE | D70: DIEGO SOARES LOPES
A71: WELDEM CARLOS PENTEADO | B71: B2C VIVO | C71: BA | D71: WEDSON FERNANDES DA SILVA
A72: ADRIANO NERIS DE OLIVEIRA | D72: R2T
A73: B2B CE | C73: CE | D73: BALDE
A74: GENILSON MOTA GALINDO | B74: B2B VIVO | C74: PE | D74: RICARDO ALVES DOS SANTOS
A75: Romualdo De Oliveira Santos | B75: B2B VIVO | C75: PE | D75: RICARDO ALVES DOS SANTOS
A76: JARDIAN PEREIRA DA SILVA | B76: B2B VIVO | C76: RN | D76: DIEGO SOARES LOPES
A77: B2B PB | C77: PB | D77: BALDE
A78: B2B RN | C78: RN | D78: BALDE
A79: B2B SE | C79: SE | D79: BALDE
A80: B2B VIVO BA. | C80: BA | D80: BALDE
A81: BA VIVO CAPITAL | C81: BA | D81: BALDE
A82: ELTON LUIZ CARVALHO DO AMARAL | C82: PE | D82: RICARDO ALVES DOS SANTOS | F82: Leonardo Oliveira
A83: GABRYEL DE MIRANDA AYRES | C83: PB | D83: MÓVEL
A84: ICOMON - ADRIANO GOMES DOS SANTOS | D84: ICOMON
A85: ICOMON - AFRANIO SILVA DE FIGUEIREDO | D85: ICOMON
A86: ICOMON - ALAN LIMA DE SOUZA | D86: ICOMON
A87: ICOMON - ALBERICO SIMPLIANO FERREIRA | D87: ICOMON
A88: ICOMON - ALBERTO SAMPAIO BEZERRA | D88: ICOMON
A89: ICOMON - ALCIDES GOMES DA SILVA FILHO | D89: ICOMON
A90: ICOMON - ALEF BRUNO PAULINO DE CASTRO | D90: ICOMON
A91: ICOMON - ALEX CORREIA DE FARIAS | D91: ICOMON
A92: ICOMON - ALEX FABIANO FRANCO FELIPE | D92: ICOMON
A93: ICOMON - ALEX PORTO DA CRUZ | D93: ICOMON
A94: ICOMON - ALEXANDRE JOSE DE LIRA FERREIRA | D94: ICOMON
A95: ICOMON - ALEXSANDRO CABRAL VITORINO | D95: ICOMON
... A361: ICOMON - YAN ANDERSON PEREIRA MEIRELES | D361: ICOMON
A362: JANECLEYTON RICARDO JUCA | C362: CE | D362: DIEGO SOARES LOPES
A363: LEILSON DA SILVA SANTOS | C363: PB | D363: RICARDO ALVES DOS SANTOS
A364: MARCIA DE SOUZA AMORIM | C364: BA | D364: WEDSON FERNANDES DA SILVA
A365: PERNAMBUCO | D365: BALDE
...
